[{"lat":28.7,"lng":-112.5758,"id":"gbif_1211765315","taxonomy_updated_species":"Crotalus_estebanensis","final_species":"Crotalus_estebanensis","accuracy_m":"NA","flag":"","flag_detailed":""},{"lat":28.675,"lng":-112.5583,"id":"gbif_1894920497","taxonomy_updated_species":"Crotalus_estebanensis","final_species":"Crotalus_estebanensis","accuracy_m":"70","flag":"","flag_detailed":""},{"lat":28.7083,"lng":-112.5917,"id":"gbif_1894920501","taxonomy_updated_species":"Crotalus_estebanensis","final_species":"Crotalus_estebanensis","accuracy_m":"70","flag":"","flag_detailed":""},{"lat":27.3108,"lng":-118.7903,"id":"gbif_2629952301","taxonomy_updated_species":"Crotalus_estebanensis","final_species":"Crotalus_estebanensis","accuracy_m":"NA","flag":"noLand","flag_detailed":"POTENTIAL_DUBIOUS_RECORD; DISTRIBUTION_ERROR; NO_LAND"},{"lat":28.72,"lng":-112.57,"id":"gbif_44985772","taxonomy_updated_species":"Crotalus_estebanensis","final_species":"Crotalus_estebanensis","accuracy_m":"NA","flag":"","flag_detailed":""},{"lat":28.72,"lng":-112.57,"id":"gbif_45075497","taxonomy_updated_species":"Crotalus_estebanensis","final_species":"Crotalus_estebanensis","accuracy_m":"NA","flag":"","flag_detailed":""},{"lat":28.7,"lng":-112.5758,"id":"GJV21112","taxonomy_updated_species":"Crotalus_estebanensis","final_species":"Crotalus_estebanensis","accuracy_m":"NA","flag":"","flag_detailed":""},{"lat":28.72,"lng":-112.57,"id":"GJV21113","taxonomy_updated_species":"Crotalus_estebanensis","final_species":"Crotalus_estebanensis","accuracy_m":"NA","flag":"","flag_detailed":""}]
