[{"lat":18.7479,"lng":-96.5468,"id":"CLP2353","taxonomy_updated_species":"Crotalus_mictlantecuhtli","final_species":"Crotalus_mictlantecuhtli","accuracy_m":"1000","flag":"","flag_detailed":""},{"lat":18.7479,"lng":-96.5468,"id":"CLP2354","taxonomy_updated_species":"Crotalus_mictlantecuhtli","final_species":"Crotalus_mictlantecuhtli","accuracy_m":"1000","flag":"","flag_detailed":""},{"lat":18.7479,"lng":-96.5468,"id":"CLP2355","taxonomy_updated_species":"Crotalus_mictlantecuhtli","final_species":"Crotalus_mictlantecuhtli","accuracy_m":"1000","flag":"","flag_detailed":""},{"lat":18.7479,"lng":-96.5468,"id":"CLP2385","taxonomy_updated_species":"Crotalus_mictlantecuhtli","final_species":"Crotalus_mictlantecuhtli","accuracy_m":"1000","flag":"","flag_detailed":""},{"lat":18.7479,"lng":-96.5468,"id":"CLP2386","taxonomy_updated_species":"Crotalus_mictlantecuhtli","final_species":"Crotalus_mictlantecuhtli","accuracy_m":"1000","flag":"","flag_detailed":""},{"lat":18.7479,"lng":-96.5468,"id":"CLPT1168","taxonomy_updated_species":"Crotalus_mictlantecuhtli","final_species":"Crotalus_mictlantecuhtli","accuracy_m":"1000","flag":"","flag_detailed":""},{"lat":18.7479,"lng":-96.5468,"id":"CLPT1169","taxonomy_updated_species":"Crotalus_mictlantecuhtli","final_species":"Crotalus_mictlantecuhtli","accuracy_m":"1000","flag":"","flag_detailed":""},{"lat":19.1777,"lng":-96.5411,"id":"gbif_1703164669","taxonomy_updated_species":"Crotalus_mictlantecuhtli","final_species":"Crotalus_mictlantecuhtli","accuracy_m":"7","flag":"","flag_detailed":""},{"lat":18.64,"lng":-96.8,"id":"gbif_1893319660","taxonomy_updated_species":"Crotalus_durissus","final_species":"Crotalus_mictlantecuhtli","accuracy_m":"90","flag":"updated","flag_detailed":"SPECIES_UPDATED"},{"lat":18.3908,"lng":-94.9047,"id":"gbif_1894786112","taxonomy_updated_species":"Crotalus_simus","final_species":"Crotalus_mictlantecuhtli","accuracy_m":"90","flag":"updated","flag_detailed":"SPECIES_UPDATED"},{"lat":18.0208,"lng":-94.9278,"id":"gbif_1894860713","taxonomy_updated_species":"Crotalus_durissus","final_species":"Crotalus_mictlantecuhtli","accuracy_m":"90","flag":"updated","flag_detailed":"SPECIES_UPDATED"},{"lat":18.7433,"lng":-96.7833,"id":"gbif_1894860715","taxonomy_updated_species":"Crotalus_durissus","final_species":"Crotalus_mictlantecuhtli","accuracy_m":"90","flag":"updated","flag_detailed":"SPECIES_UPDATED"},{"lat":18.9617,"lng":-96.7283,"id":"gbif_1894860717","taxonomy_updated_species":"Crotalus_durissus","final_species":"Crotalus_mictlantecuhtli","accuracy_m":"80","flag":"updated","flag_detailed":"SPECIES_UPDATED"},{"lat":19.175,"lng":-96.1583,"id":"gbif_1894954056","taxonomy_updated_species":"Crotalus_durissus","final_species":"Crotalus_mictlantecuhtli","accuracy_m":"80","flag":"updated","flag_detailed":"SPECIES_UPDATED"},{"lat":18.975,"lng":-96.7417,"id":"gbif_1894954084","taxonomy_updated_species":"Crotalus_durissus","final_species":"Crotalus_mictlantecuhtli","accuracy_m":"80","flag":"updated","flag_detailed":"SPECIES_UPDATED"},{"lat":18.4583,"lng":-96.3583,"id":"gbif_1894954086","taxonomy_updated_species":"Crotalus_durissus","final_species":"Crotalus_mictlantecuhtli","accuracy_m":"90","flag":"updated","flag_detailed":"SPECIES_UPDATED"},{"lat":18.975,"lng":-96.7417,"id":"gbif_1894954113","taxonomy_updated_species":"Crotalus_durissus","final_species":"Crotalus_mictlantecuhtli","accuracy_m":"80","flag":"updated","flag_detailed":"SPECIES_UPDATED"},{"lat":18.025,"lng":-94.9583,"id":"gbif_1894954127","taxonomy_updated_species":"Crotalus_durissus","final_species":"Crotalus_mictlantecuhtli","accuracy_m":"90","flag":"updated","flag_detailed":"SPECIES_UPDATED"},{"lat":19.3056,"lng":-96.3134,"id":"gbif_1933552135","taxonomy_updated_species":"Crotalus_mictlantecuhtli","final_species":"Crotalus_mictlantecuhtli","accuracy_m":"704","flag":"","flag_detailed":""},{"lat":18.8882,"lng":-96.6877,"id":"gbif_1978440544","taxonomy_updated_species":"Crotalus_mictlantecuhtli","final_species":"Crotalus_mictlantecuhtli","accuracy_m":"30615","flag":"","flag_detailed":""},{"lat":17.7556,"lng":-93.6621,"id":"gbif_1993755763","taxonomy_updated_species":"Crotalus_mictlantecuhtli","final_species":"Crotalus_mictlantecuhtli","accuracy_m":"7","flag":"","flag_detailed":""},{"lat":19.06,"lng":-96.075,"id":"gbif_2234850542","taxonomy_updated_species":"Crotalus_durissus","final_species":"Crotalus_mictlantecuhtli","accuracy_m":"NA","flag":"updated","flag_detailed":"SPECIES_UPDATED"},{"lat":19.0511,"lng":-95.9844,"id":"gbif_2273227613","taxonomy_updated_species":"Crotalus_mictlantecuhtli","final_species":"Crotalus_mictlantecuhtli","accuracy_m":"2768","flag":"","flag_detailed":""},{"lat":18.4498,"lng":-96.3599,"id":"gbif_2598331651","taxonomy_updated_species":"Crotalus_mictlantecuhtli","final_species":"Crotalus_mictlantecuhtli","accuracy_m":"NA","flag":"","flag_detailed":""},{"lat":19.0673,"lng":-96.0902,"id":"gbif_2826510777","taxonomy_updated_species":"Crotalus_mictlantecuhtli","final_species":"Crotalus_mictlantecuhtli","accuracy_m":"20","flag":"","flag_detailed":""},{"lat":19.0541,"lng":-96.0118,"id":"gbif_2850754710","taxonomy_updated_species":"Crotalus_mictlantecuhtli","final_species":"Crotalus_mictlantecuhtli","accuracy_m":"NA","flag":"","flag_detailed":""},{"lat":19.0667,"lng":-96.0783,"id":"gbif_3039144822","taxonomy_updated_species":"Crotalus_mictlantecuhtli","final_species":"Crotalus_mictlantecuhtli","accuracy_m":"189","flag":"","flag_detailed":""},{"lat":19.1822,"lng":-96.5403,"id":"gbif_3079475401","taxonomy_updated_species":"Crotalus_mictlantecuhtli","final_species":"Crotalus_mictlantecuhtli","accuracy_m":"NA","flag":"","flag_detailed":""},{"lat":19.1779,"lng":-96.5412,"id":"gbif_3079482391","taxonomy_updated_species":"Crotalus_mictlantecuhtli","final_species":"Crotalus_mictlantecuhtli","accuracy_m":"NA","flag":"","flag_detailed":""},{"lat":19.1804,"lng":-96.5412,"id":"gbif_3079581333","taxonomy_updated_species":"Crotalus_mictlantecuhtli","final_species":"Crotalus_mictlantecuhtli","accuracy_m":"NA","flag":"","flag_detailed":""},{"lat":19.1883,"lng":-96.14,"id":"gbif_44970068","taxonomy_updated_species":"Crotalus_simus","final_species":"Crotalus_mictlantecuhtli","accuracy_m":"NA","flag":"updated","flag_detailed":"SPECIES_UPDATED"},{"lat":19.1023,"lng":-96.1034,"id":"gbif_657488501","taxonomy_updated_species":"Crotalus_durissus","final_species":"Crotalus_mictlantecuhtli","accuracy_m":"NA","flag":"updated","flag_detailed":"SPECIES_UPDATED"},{"lat":19.1883,"lng":-96.14,"id":"GJV35454","taxonomy_updated_species":"Crotalus_simus","final_species":"Crotalus_mictlantecuhtli","accuracy_m":"NA","flag":"updated","flag_detailed":"SPECIES_UPDATED"},{"lat":18.3908,"lng":-94.9047,"id":"GJV35455","taxonomy_updated_species":"Crotalus_simus","final_species":"Crotalus_mictlantecuhtli","accuracy_m":"NA","flag":"updated","flag_detailed":"SPECIES_UPDATED"},{"lat":17.999,"lng":-94.637,"id":"GJV38390","taxonomy_updated_species":"Crotalus_culminatus","final_species":"Crotalus_mictlantecuhtli","accuracy_m":"NA","flag":"updated","flag_detailed":"SPECIES_UPDATED"}]
