[{"lat":16.967,"lng":-88.983,"id":"EPH0070","taxonomy_updated_species":"Metlapilcoatlus_mexicanus","final_species":"Metlapilcoatlus_mexicanus","accuracy_m":"NA","flag":"","flag_detailed":""},{"lat":16.933,"lng":-89.117,"id":"EPH0071","taxonomy_updated_species":"Metlapilcoatlus_mexicanus","final_species":"Metlapilcoatlus_mexicanus","accuracy_m":"NA","flag":"","flag_detailed":""},{"lat":17.2,"lng":-89.017,"id":"EPH0072","taxonomy_updated_species":"Metlapilcoatlus_mexicanus","final_species":"Metlapilcoatlus_mexicanus","accuracy_m":"NA","flag":"","flag_detailed":""},{"lat":16.817,"lng":-88.617,"id":"EPH0073","taxonomy_updated_species":"Metlapilcoatlus_mexicanus","final_species":"Metlapilcoatlus_mexicanus","accuracy_m":"NA","flag":"","flag_detailed":""},{"lat":16.883,"lng":-88.917,"id":"EPH0074","taxonomy_updated_species":"Metlapilcoatlus_mexicanus","final_species":"Metlapilcoatlus_mexicanus","accuracy_m":"NA","flag":"","flag_detailed":""},{"lat":16.783,"lng":-89.15,"id":"EPH0075","taxonomy_updated_species":"Metlapilcoatlus_mexicanus","final_species":"Metlapilcoatlus_mexicanus","accuracy_m":"NA","flag":"","flag_detailed":""},{"lat":16.7,"lng":-88.633,"id":"EPH0076","taxonomy_updated_species":"Metlapilcoatlus_mexicanus","final_species":"Metlapilcoatlus_mexicanus","accuracy_m":"NA","flag":"","flag_detailed":""},{"lat":17.05,"lng":-88.567,"id":"EPH0077","taxonomy_updated_species":"Metlapilcoatlus_mexicanus","final_species":"Metlapilcoatlus_mexicanus","accuracy_m":"NA","flag":"","flag_detailed":""},{"lat":16.267,"lng":-89.05,"id":"EPH0078","taxonomy_updated_species":"Metlapilcoatlus_mexicanus","final_species":"Metlapilcoatlus_mexicanus","accuracy_m":"NA","flag":"","flag_detailed":""},{"lat":16.433,"lng":-89.05,"id":"EPH0079","taxonomy_updated_species":"Metlapilcoatlus_mexicanus","final_species":"Metlapilcoatlus_mexicanus","accuracy_m":"NA","flag":"","flag_detailed":""},{"lat":16.03,"lng":-90.21,"id":"EPH0080","taxonomy_updated_species":"Metlapilcoatlus_mexicanus","final_species":"Metlapilcoatlus_mexicanus","accuracy_m":"NA","flag":"","flag_detailed":""},{"lat":16.35,"lng":-89.433,"id":"EPH0081","taxonomy_updated_species":"Metlapilcoatlus_mexicanus","final_species":"Metlapilcoatlus_mexicanus","accuracy_m":"NA","flag":"","flag_detailed":""},{"lat":16.48,"lng":-90.162,"id":"EPH0082","taxonomy_updated_species":"Metlapilcoatlus_mexicanus","final_species":"Metlapilcoatlus_mexicanus","accuracy_m":"NA","flag":"","flag_detailed":""},{"lat":16.783,"lng":-90.117,"id":"EPH0083","taxonomy_updated_species":"Metlapilcoatlus_mexicanus","final_species":"Metlapilcoatlus_mexicanus","accuracy_m":"NA","flag":"","flag_detailed":""},{"lat":17.2,"lng":-91.25,"id":"EPH0084","taxonomy_updated_species":"Metlapilcoatlus_mexicanus","final_species":"Metlapilcoatlus_mexicanus","accuracy_m":"NA","flag":"","flag_detailed":""},{"lat":17.2,"lng":-90.2,"id":"EPH0085","taxonomy_updated_species":"Metlapilcoatlus_mexicanus","final_species":"Metlapilcoatlus_mexicanus","accuracy_m":"NA","flag":"geoDist","flag_detailed":"POTENTIAL_DUBIOUS_RECORD; DISTRIBUTION_ERROR; POINT_OUTSIDE_DISTRIBUTION; ADDITIONAL_CHECKS_NEEDED"},{"lat":16.517,"lng":-90.167,"id":"EPH0086","taxonomy_updated_species":"Metlapilcoatlus_mexicanus","final_species":"Metlapilcoatlus_mexicanus","accuracy_m":"NA","flag":"","flag_detailed":""},{"lat":16.683,"lng":-90.033,"id":"EPH0087","taxonomy_updated_species":"Metlapilcoatlus_mexicanus","final_species":"Metlapilcoatlus_mexicanus","accuracy_m":"NA","flag":"","flag_detailed":""},{"lat":15.948,"lng":-90.117,"id":"EPH0088","taxonomy_updated_species":"Metlapilcoatlus_mexicanus","final_species":"Metlapilcoatlus_mexicanus","accuracy_m":"NA","flag":"","flag_detailed":""},{"lat":12.92,"lng":-85.92,"id":"EPH0089","taxonomy_updated_species":"Metlapilcoatlus_mexicanus","final_species":"Metlapilcoatlus_mexicanus","accuracy_m":"NA","flag":"dubious","flag_detailed":"POTENTIAL_DUBIOUS_RECORD; DISTRIBUTION_ERROR; POINT_OUTSIDE_DISTRIBUTION; DISTANCE_EXCEEDS_50KM; UNCERTAIN_SPECIES_ID; ADDITIONAL_CHECKS_NEEDED"},{"lat":15.5558,"lng":-88.6221,"id":"gbif_1061350912","taxonomy_updated_species":"Metlapilcoatlus_nummifer","final_species":"Metlapilcoatlus_mexicanus","accuracy_m":"701065","flag":"updated","flag_detailed":"SPECIES_UPDATED"},{"lat":15.5558,"lng":-88.6221,"id":"gbif_1061350955","taxonomy_updated_species":"Metlapilcoatlus_nummifer","final_species":"Metlapilcoatlus_mexicanus","accuracy_m":"701065","flag":"updated","flag_detailed":"SPECIES_UPDATED"},{"lat":16.9074,"lng":-92.0933,"id":"gbif_1061360916","taxonomy_updated_species":"Metlapilcoatlus_nummifer","final_species":"Metlapilcoatlus_mexicanus","accuracy_m":"NA","flag":"updated","flag_detailed":"SPECIES_UPDATED"},{"lat":16.9074,"lng":-92.0933,"id":"gbif_1061360956","taxonomy_updated_species":"Metlapilcoatlus_nummifer","final_species":"Metlapilcoatlus_mexicanus","accuracy_m":"NA","flag":"updated","flag_detailed":"SPECIES_UPDATED"},{"lat":16.2508,"lng":-92.1333,"id":"gbif_1061360962","taxonomy_updated_species":"Metlapilcoatlus_nummifer","final_species":"Metlapilcoatlus_mexicanus","accuracy_m":"NA","flag":"updated","flag_detailed":"SPECIES_UPDATED"},{"lat":17.2807,"lng":-95.11,"id":"gbif_1061374905","taxonomy_updated_species":"Metlapilcoatlus_mexicanus","final_species":"Metlapilcoatlus_mexicanus","accuracy_m":"NA","flag":"dubious","flag_detailed":"POTENTIAL_DUBIOUS_RECORD; DISTRIBUTION_ERROR; POINT_OUTSIDE_DISTRIBUTION; DISTANCE_EXCEEDS_50KM; UNCERTAIN_SPECIES_ID; ADDITIONAL_CHECKS_NEEDED"},{"lat":15.505,"lng":-90.8563,"id":"gbif_1145579508","taxonomy_updated_species":"Metlapilcoatlus_mexicanus","final_species":"Metlapilcoatlus_mexicanus","accuracy_m":"10","flag":"","flag_detailed":""},{"lat":15.1167,"lng":-88.9333,"id":"gbif_1145581196","taxonomy_updated_species":"Metlapilcoatlus_mexicanus","final_species":"Metlapilcoatlus_mexicanus","accuracy_m":"2700","flag":"","flag_detailed":""},{"lat":8.8198,"lng":-82.9703,"id":"gbif_1229583819","taxonomy_updated_species":"Metlapilcoatlus_nummifer","final_species":"Metlapilcoatlus_mexicanus","accuracy_m":"4023","flag":"updated","flag_detailed":"SPECIES_UPDATED"},{"lat":15.5302,"lng":-87.2939,"id":"gbif_1317565040","taxonomy_updated_species":"Metlapilcoatlus_mexicanus","final_species":"Metlapilcoatlus_mexicanus","accuracy_m":"NA","flag":"","flag_detailed":""},{"lat":17.18,"lng":-91.25,"id":"gbif_1318595211","taxonomy_updated_species":"Metlapilcoatlus_mexicanus","final_species":"Metlapilcoatlus_mexicanus","accuracy_m":"NA","flag":"","flag_detailed":""},{"lat":15.13,"lng":-88.9,"id":"gbif_1318788869","taxonomy_updated_species":"Metlapilcoatlus_mexicanus","final_species":"Metlapilcoatlus_mexicanus","accuracy_m":"NA","flag":"","flag_detailed":""},{"lat":15.5302,"lng":-87.2939,"id":"gbif_1319562378","taxonomy_updated_species":"Metlapilcoatlus_mexicanus","final_species":"Metlapilcoatlus_mexicanus","accuracy_m":"NA","flag":"","flag_detailed":""},{"lat":15.5,"lng":-88.03,"id":"gbif_1319938677","taxonomy_updated_species":"Metlapilcoatlus_nummifer","final_species":"Metlapilcoatlus_mexicanus","accuracy_m":"5569","flag":"updated","flag_detailed":"SPECIES_UPDATED"},{"lat":15.5,"lng":-88.03,"id":"gbif_1319988020","taxonomy_updated_species":"Metlapilcoatlus_nummifer","final_species":"Metlapilcoatlus_mexicanus","accuracy_m":"5569","flag":"updated","flag_detailed":"SPECIES_UPDATED"},{"lat":15.7833,"lng":-87.45,"id":"gbif_1320014362","taxonomy_updated_species":"Metlapilcoatlus_nummifer","final_species":"Metlapilcoatlus_mexicanus","accuracy_m":"4567","flag":"updated","flag_detailed":"SPECIES_UPDATED"},{"lat":15.7833,"lng":-87.45,"id":"gbif_1320422573","taxonomy_updated_species":"Metlapilcoatlus_nummifer","final_species":"Metlapilcoatlus_mexicanus","accuracy_m":"4567","flag":"updated","flag_detailed":"SPECIES_UPDATED"},{"lat":15.7,"lng":-87.4667,"id":"gbif_1320568031","taxonomy_updated_species":"Metlapilcoatlus_nummifer","final_species":"Metlapilcoatlus_mexicanus","accuracy_m":"3568","flag":"updated","flag_detailed":"SPECIES_UPDATED"},{"lat":15.7833,"lng":-87.45,"id":"gbif_1320864919","taxonomy_updated_species":"Metlapilcoatlus_nummifer","final_species":"Metlapilcoatlus_mexicanus","accuracy_m":"4567","flag":"updated","flag_detailed":"SPECIES_UPDATED"},{"lat":15.7833,"lng":-87.45,"id":"gbif_1321023429","taxonomy_updated_species":"Metlapilcoatlus_nummifer","final_species":"Metlapilcoatlus_mexicanus","accuracy_m":"4567","flag":"updated","flag_detailed":"SPECIES_UPDATED"},{"lat":17.18,"lng":-91.25,"id":"gbif_1321845015","taxonomy_updated_species":"Metlapilcoatlus_mexicanus","final_species":"Metlapilcoatlus_mexicanus","accuracy_m":"NA","flag":"","flag_detailed":""},{"lat":15.7833,"lng":-87.45,"id":"gbif_1321980225","taxonomy_updated_species":"Metlapilcoatlus_nummifer","final_species":"Metlapilcoatlus_mexicanus","accuracy_m":"4567","flag":"updated","flag_detailed":"SPECIES_UPDATED"},{"lat":15.7833,"lng":-87.45,"id":"gbif_1322126949","taxonomy_updated_species":"Metlapilcoatlus_nummifer","final_species":"Metlapilcoatlus_mexicanus","accuracy_m":"4567","flag":"updated","flag_detailed":"SPECIES_UPDATED"},{"lat":15.7833,"lng":-87.45,"id":"gbif_1322455393","taxonomy_updated_species":"Metlapilcoatlus_nummifer","final_species":"Metlapilcoatlus_mexicanus","accuracy_m":"4567","flag":"updated","flag_detailed":"SPECIES_UPDATED"},{"lat":10.5,"lng":-84.5,"id":"gbif_1852446200","taxonomy_updated_species":"Metlapilcoatlus_nummifer","final_species":"Metlapilcoatlus_mexicanus","accuracy_m":"NA","flag":"updated","flag_detailed":"SPECIES_UPDATED"},{"lat":16.2511,"lng":-92.1342,"id":"gbif_1893319887","taxonomy_updated_species":"Metlapilcoatlus_nummifer","final_species":"Metlapilcoatlus_mexicanus","accuracy_m":"100","flag":"updated","flag_detailed":"SPECIES_UPDATED"},{"lat":16.2511,"lng":-92.1342,"id":"gbif_1893319933","taxonomy_updated_species":"Metlapilcoatlus_nummifer","final_species":"Metlapilcoatlus_mexicanus","accuracy_m":"100","flag":"updated","flag_detailed":"SPECIES_UPDATED"},{"lat":16.2511,"lng":-92.1342,"id":"gbif_1893320001","taxonomy_updated_species":"Metlapilcoatlus_nummifer","final_species":"Metlapilcoatlus_mexicanus","accuracy_m":"100","flag":"updated","flag_detailed":"SPECIES_UPDATED"},{"lat":16.2747,"lng":-93.7264,"id":"gbif_1894740970","taxonomy_updated_species":"Metlapilcoatlus_nummifer","final_species":"Metlapilcoatlus_mexicanus","accuracy_m":"100","flag":"updated","flag_detailed":"POTENTIAL_DUBIOUS_RECORD; DISTRIBUTION_ERROR; POINT_OUTSIDE_DISTRIBUTION; SPECIES_UPDATED; ADDITIONAL_CHECKS_NEEDED"},{"lat":16.725,"lng":-92.5417,"id":"gbif_1894911908","taxonomy_updated_species":"Metlapilcoatlus_mexicanus","final_species":"Metlapilcoatlus_mexicanus","accuracy_m":"100","flag":"","flag_detailed":""},{"lat":16.675,"lng":-93.7583,"id":"gbif_1894911918","taxonomy_updated_species":"Metlapilcoatlus_mexicanus","final_species":"Metlapilcoatlus_mexicanus","accuracy_m":"100","flag":"","flag_detailed":""},{"lat":16.6583,"lng":-92.5583,"id":"gbif_1894911921","taxonomy_updated_species":"Metlapilcoatlus_mexicanus","final_species":"Metlapilcoatlus_mexicanus","accuracy_m":"100","flag":"","flag_detailed":""},{"lat":16.2583,"lng":-92.1417,"id":"gbif_1894929305","taxonomy_updated_species":"Metlapilcoatlus_nummifer","final_species":"Metlapilcoatlus_mexicanus","accuracy_m":"100","flag":"updated","flag_detailed":"SPECIES_UPDATED"},{"lat":16.675,"lng":-93.7583,"id":"gbif_1894958861","taxonomy_updated_species":"Metlapilcoatlus_nummifer","final_species":"Metlapilcoatlus_mexicanus","accuracy_m":"100","flag":"updated","flag_detailed":"SPECIES_UPDATED"},{"lat":17.175,"lng":-92.9083,"id":"gbif_1894958866","taxonomy_updated_species":"Metlapilcoatlus_nummifer","final_species":"Metlapilcoatlus_mexicanus","accuracy_m":"90","flag":"updated","flag_detailed":"SPECIES_UPDATED"},{"lat":16.9083,"lng":-91.7583,"id":"gbif_1894958881","taxonomy_updated_species":"Metlapilcoatlus_nummifer","final_species":"Metlapilcoatlus_mexicanus","accuracy_m":"90","flag":"updated","flag_detailed":"SPECIES_UPDATED"},{"lat":16.675,"lng":-93.7583,"id":"gbif_1894958890","taxonomy_updated_species":"Metlapilcoatlus_nummifer","final_species":"Metlapilcoatlus_mexicanus","accuracy_m":"100","flag":"updated","flag_detailed":"SPECIES_UPDATED"},{"lat":16.9886,"lng":-91.5632,"id":"gbif_2629190326","taxonomy_updated_species":"Metlapilcoatlus_nummifer","final_species":"Metlapilcoatlus_mexicanus","accuracy_m":"NA","flag":"updated","flag_detailed":"SPECIES_UPDATED"},{"lat":16.125,"lng":-91.7069,"id":"gbif_2629266778","taxonomy_updated_species":"Metlapilcoatlus_nummifer","final_species":"Metlapilcoatlus_mexicanus","accuracy_m":"NA","flag":"updated","flag_detailed":"SPECIES_UPDATED"},{"lat":16.1264,"lng":-91.7306,"id":"gbif_2629269680","taxonomy_updated_species":"Metlapilcoatlus_nummifer","final_species":"Metlapilcoatlus_mexicanus","accuracy_m":"NA","flag":"updated","flag_detailed":"SPECIES_UPDATED"},{"lat":16.1264,"lng":-91.7306,"id":"gbif_2629270636","taxonomy_updated_species":"Metlapilcoatlus_nummifer","final_species":"Metlapilcoatlus_mexicanus","accuracy_m":"NA","flag":"updated","flag_detailed":"SPECIES_UPDATED"},{"lat":17.5583,"lng":-92.9583,"id":"gbif_2630242774","taxonomy_updated_species":"Metlapilcoatlus_nummifer","final_species":"Metlapilcoatlus_mexicanus","accuracy_m":"90","flag":"updated","flag_detailed":"SPECIES_UPDATED"},{"lat":16.2511,"lng":-92.1342,"id":"gbif_2630331046","taxonomy_updated_species":"Metlapilcoatlus_mexicanus","final_species":"Metlapilcoatlus_mexicanus","accuracy_m":"100","flag":"","flag_detailed":""},{"lat":16.9842,"lng":-93.7728,"id":"gbif_2630339361","taxonomy_updated_species":"Metlapilcoatlus_mexicanus","final_species":"Metlapilcoatlus_mexicanus","accuracy_m":"90","flag":"","flag_detailed":""},{"lat":16.4889,"lng":-92.2333,"id":"gbif_2630341366","taxonomy_updated_species":"Metlapilcoatlus_nummifer","final_species":"Metlapilcoatlus_mexicanus","accuracy_m":"100","flag":"updated","flag_detailed":"SPECIES_UPDATED"},{"lat":16.0981,"lng":-91.6944,"id":"gbif_2630353053","taxonomy_updated_species":"Metlapilcoatlus_occiduus","final_species":"Metlapilcoatlus_mexicanus","accuracy_m":"100","flag":"updated","flag_detailed":"SPECIES_UPDATED"},{"lat":17.1592,"lng":-92.8992,"id":"gbif_2630356329","taxonomy_updated_species":"Metlapilcoatlus_mexicanus","final_species":"Metlapilcoatlus_mexicanus","accuracy_m":"90","flag":"","flag_detailed":""},{"lat":16.4889,"lng":-92.2333,"id":"gbif_2630359981","taxonomy_updated_species":"Metlapilcoatlus_mexicanus","final_species":"Metlapilcoatlus_mexicanus","accuracy_m":"100","flag":"","flag_detailed":""},{"lat":16.7292,"lng":-92.7194,"id":"gbif_2630371577","taxonomy_updated_species":"Metlapilcoatlus_mexicanus","final_species":"Metlapilcoatlus_mexicanus","accuracy_m":"100","flag":"","flag_detailed":""},{"lat":16.2511,"lng":-92.1342,"id":"gbif_2630372557","taxonomy_updated_species":"Metlapilcoatlus_nummifer","final_species":"Metlapilcoatlus_mexicanus","accuracy_m":"100","flag":"updated","flag_detailed":"SPECIES_UPDATED"},{"lat":16.6486,"lng":-92.5444,"id":"gbif_2630376576","taxonomy_updated_species":"Metlapilcoatlus_mexicanus","final_species":"Metlapilcoatlus_mexicanus","accuracy_m":"100","flag":"","flag_detailed":""},{"lat":16.8922,"lng":-93.4525,"id":"gbif_2630379675","taxonomy_updated_species":"Metlapilcoatlus_mexicanus","final_species":"Metlapilcoatlus_mexicanus","accuracy_m":"90","flag":"","flag_detailed":""},{"lat":16.1225,"lng":-91.7075,"id":"gbif_2630399029","taxonomy_updated_species":"Metlapilcoatlus_nummifer","final_species":"Metlapilcoatlus_mexicanus","accuracy_m":"100","flag":"updated","flag_detailed":"SPECIES_UPDATED"},{"lat":9.8322,"lng":-83.6073,"id":"gbif_2832193781","taxonomy_updated_species":"Metlapilcoatlus_nummifer","final_species":"Metlapilcoatlus_mexicanus","accuracy_m":"1000","flag":"updated","flag_detailed":"SPECIES_UPDATED"},{"lat":16.9886,"lng":-91.5632,"id":"gbif_3306273940","taxonomy_updated_species":"Metlapilcoatlus_nummifer","final_species":"Metlapilcoatlus_mexicanus","accuracy_m":"NA","flag":"updated","flag_detailed":"SPECIES_UPDATED"},{"lat":15.4,"lng":-88.15,"id":"gbif_476491985","taxonomy_updated_species":"Metlapilcoatlus_mexicanus","final_species":"Metlapilcoatlus_mexicanus","accuracy_m":"4569","flag":"","flag_detailed":""},{"lat":-12.4996,"lng":-54.0332,"id":"gbif_476492015","taxonomy_updated_species":"Metlapilcoatlus_mexicanus","final_species":"Metlapilcoatlus_mexicanus","accuracy_m":"2359900","flag":"dubious","flag_detailed":"POTENTIAL_DUBIOUS_RECORD; DISTRIBUTION_ERROR; POINT_OUTSIDE_DISTRIBUTION; DISTANCE_EXCEEDS_50KM; UNCERTAIN_SPECIES_ID; ADDITIONAL_CHECKS_NEEDED"},{"lat":15.7,"lng":-87.467,"id":"gbif_476493086","taxonomy_updated_species":"Metlapilcoatlus_mexicanus","final_species":"Metlapilcoatlus_mexicanus","accuracy_m":"3568","flag":"","flag_detailed":""},{"lat":15.7,"lng":-87.467,"id":"gbif_476493087","taxonomy_updated_species":"Metlapilcoatlus_mexicanus","final_species":"Metlapilcoatlus_mexicanus","accuracy_m":"3568","flag":"","flag_detailed":""},{"lat":15.5,"lng":-88.0333,"id":"gbif_476493108","taxonomy_updated_species":"Metlapilcoatlus_mexicanus","final_species":"Metlapilcoatlus_mexicanus","accuracy_m":"5569","flag":"","flag_detailed":""},{"lat":15.4,"lng":-88.15,"id":"gbif_476493214","taxonomy_updated_species":"Metlapilcoatlus_nummifer","final_species":"Metlapilcoatlus_mexicanus","accuracy_m":"4569","flag":"updated","flag_detailed":"SPECIES_UPDATED"},{"lat":15.4,"lng":-88.15,"id":"gbif_476493215","taxonomy_updated_species":"Metlapilcoatlus_nummifer","final_species":"Metlapilcoatlus_mexicanus","accuracy_m":"4569","flag":"updated","flag_detailed":"SPECIES_UPDATED"},{"lat":17.1748,"lng":-91.2511,"id":"gbif_476495758","taxonomy_updated_species":"Metlapilcoatlus_mexicanus","final_species":"Metlapilcoatlus_mexicanus","accuracy_m":"11119","flag":"","flag_detailed":""},{"lat":15.4,"lng":-88.15,"id":"gbif_476658328","taxonomy_updated_species":"Metlapilcoatlus_mexicanus","final_species":"Metlapilcoatlus_mexicanus","accuracy_m":"4569","flag":"","flag_detailed":""},{"lat":15.4,"lng":-88.15,"id":"gbif_476658432","taxonomy_updated_species":"Metlapilcoatlus_mexicanus","final_species":"Metlapilcoatlus_mexicanus","accuracy_m":"4569","flag":"","flag_detailed":""},{"lat":15.4,"lng":-88.15,"id":"gbif_476658433","taxonomy_updated_species":"Metlapilcoatlus_mexicanus","final_species":"Metlapilcoatlus_mexicanus","accuracy_m":"4569","flag":"","flag_detailed":""},{"lat":15.4,"lng":-88.15,"id":"gbif_476658434","taxonomy_updated_species":"Metlapilcoatlus_mexicanus","final_species":"Metlapilcoatlus_mexicanus","accuracy_m":"4569","flag":"","flag_detailed":""},{"lat":15.4,"lng":-88.15,"id":"gbif_476658435","taxonomy_updated_species":"Metlapilcoatlus_mexicanus","final_species":"Metlapilcoatlus_mexicanus","accuracy_m":"4569","flag":"","flag_detailed":""},{"lat":15.4,"lng":-88.15,"id":"gbif_476658538","taxonomy_updated_species":"Metlapilcoatlus_mexicanus","final_species":"Metlapilcoatlus_mexicanus","accuracy_m":"4569","flag":"","flag_detailed":""},{"lat":14.6333,"lng":-88.1333,"id":"gbif_476661572","taxonomy_updated_species":"Metlapilcoatlus_nummifer","final_species":"Metlapilcoatlus_mexicanus","accuracy_m":"3036","flag":"updated","flag_detailed":"POTENTIAL_DUBIOUS_RECORD; DISTRIBUTION_ERROR; POINT_OUTSIDE_DISTRIBUTION; SPECIES_UPDATED; ADDITIONAL_CHECKS_NEEDED"},{"lat":15.7,"lng":-87.467,"id":"gbif_476664357","taxonomy_updated_species":"Metlapilcoatlus_mexicanus","final_species":"Metlapilcoatlus_mexicanus","accuracy_m":"3568","flag":"","flag_detailed":""},{"lat":15.7,"lng":-87.467,"id":"gbif_476664358","taxonomy_updated_species":"Metlapilcoatlus_mexicanus","final_species":"Metlapilcoatlus_mexicanus","accuracy_m":"3568","flag":"","flag_detailed":""},{"lat":15.7,"lng":-87.467,"id":"gbif_476664468","taxonomy_updated_species":"Metlapilcoatlus_mexicanus","final_species":"Metlapilcoatlus_mexicanus","accuracy_m":"3568","flag":"","flag_detailed":""},{"lat":15.7,"lng":-87.467,"id":"gbif_476664469","taxonomy_updated_species":"Metlapilcoatlus_mexicanus","final_species":"Metlapilcoatlus_mexicanus","accuracy_m":"3568","flag":"","flag_detailed":""},{"lat":15.7,"lng":-87.467,"id":"gbif_476664472","taxonomy_updated_species":"Metlapilcoatlus_mexicanus","final_species":"Metlapilcoatlus_mexicanus","accuracy_m":"3568","flag":"","flag_detailed":""},{"lat":15.5,"lng":-88.0333,"id":"gbif_476664578","taxonomy_updated_species":"Metlapilcoatlus_mexicanus","final_species":"Metlapilcoatlus_mexicanus","accuracy_m":"5569","flag":"","flag_detailed":""},{"lat":15.5,"lng":-88.0333,"id":"gbif_476664928","taxonomy_updated_species":"Metlapilcoatlus_mexicanus","final_species":"Metlapilcoatlus_mexicanus","accuracy_m":"5569","flag":"","flag_detailed":""},{"lat":15.5,"lng":-88.0333,"id":"gbif_476664929","taxonomy_updated_species":"Metlapilcoatlus_mexicanus","final_species":"Metlapilcoatlus_mexicanus","accuracy_m":"5569","flag":"","flag_detailed":""},{"lat":15.5,"lng":-88.0333,"id":"gbif_476664930","taxonomy_updated_species":"Metlapilcoatlus_mexicanus","final_species":"Metlapilcoatlus_mexicanus","accuracy_m":"5569","flag":"","flag_detailed":""},{"lat":15.5,"lng":-88.0333,"id":"gbif_476665035","taxonomy_updated_species":"Metlapilcoatlus_mexicanus","final_species":"Metlapilcoatlus_mexicanus","accuracy_m":"5569","flag":"","flag_detailed":""},{"lat":15.5,"lng":-88.0333,"id":"gbif_476665036","taxonomy_updated_species":"Metlapilcoatlus_mexicanus","final_species":"Metlapilcoatlus_mexicanus","accuracy_m":"5569","flag":"","flag_detailed":""},{"lat":15.5,"lng":-88.0333,"id":"gbif_476665037","taxonomy_updated_species":"Metlapilcoatlus_mexicanus","final_species":"Metlapilcoatlus_mexicanus","accuracy_m":"5569","flag":"","flag_detailed":""},{"lat":15.5,"lng":-88.0333,"id":"gbif_476665038","taxonomy_updated_species":"Metlapilcoatlus_mexicanus","final_species":"Metlapilcoatlus_mexicanus","accuracy_m":"5569","flag":"","flag_detailed":""},{"lat":14.7667,"lng":-87.7833,"id":"gbif_476669634","taxonomy_updated_species":"Metlapilcoatlus_mexicanus","final_species":"Metlapilcoatlus_mexicanus","accuracy_m":"3036","flag":"","flag_detailed":""},{"lat":15.4,"lng":-88.15,"id":"gbif_476669635","taxonomy_updated_species":"Metlapilcoatlus_nummifer","final_species":"Metlapilcoatlus_mexicanus","accuracy_m":"4569","flag":"updated","flag_detailed":"SPECIES_UPDATED"},{"lat":15.4,"lng":-88.15,"id":"gbif_476669637","taxonomy_updated_species":"Metlapilcoatlus_nummifer","final_species":"Metlapilcoatlus_mexicanus","accuracy_m":"4569","flag":"updated","flag_detailed":"SPECIES_UPDATED"},{"lat":15.4,"lng":-88.15,"id":"gbif_476669640","taxonomy_updated_species":"Metlapilcoatlus_nummifer","final_species":"Metlapilcoatlus_mexicanus","accuracy_m":"4569","flag":"updated","flag_detailed":"SPECIES_UPDATED"},{"lat":15.4,"lng":-88.15,"id":"gbif_476669749","taxonomy_updated_species":"Metlapilcoatlus_nummifer","final_species":"Metlapilcoatlus_mexicanus","accuracy_m":"4569","flag":"updated","flag_detailed":"SPECIES_UPDATED"},{"lat":15.4,"lng":-88.15,"id":"gbif_476669750","taxonomy_updated_species":"Metlapilcoatlus_nummifer","final_species":"Metlapilcoatlus_mexicanus","accuracy_m":"4569","flag":"updated","flag_detailed":"SPECIES_UPDATED"},{"lat":15.4,"lng":-88.15,"id":"gbif_476669751","taxonomy_updated_species":"Metlapilcoatlus_nummifer","final_species":"Metlapilcoatlus_mexicanus","accuracy_m":"4569","flag":"updated","flag_detailed":"SPECIES_UPDATED"},{"lat":15.4,"lng":-88.15,"id":"gbif_476669753","taxonomy_updated_species":"Metlapilcoatlus_nummifer","final_species":"Metlapilcoatlus_mexicanus","accuracy_m":"4569","flag":"updated","flag_detailed":"SPECIES_UPDATED"},{"lat":15.4,"lng":-88.15,"id":"gbif_476669754","taxonomy_updated_species":"Metlapilcoatlus_nummifer","final_species":"Metlapilcoatlus_mexicanus","accuracy_m":"4569","flag":"updated","flag_detailed":"SPECIES_UPDATED"},{"lat":15.4,"lng":-88.15,"id":"gbif_476669860","taxonomy_updated_species":"Metlapilcoatlus_nummifer","final_species":"Metlapilcoatlus_mexicanus","accuracy_m":"4569","flag":"updated","flag_detailed":"SPECIES_UPDATED"},{"lat":15.4,"lng":-88.15,"id":"gbif_476669861","taxonomy_updated_species":"Metlapilcoatlus_nummifer","final_species":"Metlapilcoatlus_mexicanus","accuracy_m":"4569","flag":"updated","flag_detailed":"SPECIES_UPDATED"},{"lat":15.4,"lng":-88.15,"id":"gbif_476669873","taxonomy_updated_species":"Metlapilcoatlus_nummifer","final_species":"Metlapilcoatlus_mexicanus","accuracy_m":"4569","flag":"updated","flag_detailed":"SPECIES_UPDATED"},{"lat":15.4,"lng":-88.15,"id":"gbif_476669874","taxonomy_updated_species":"Metlapilcoatlus_nummifer","final_species":"Metlapilcoatlus_mexicanus","accuracy_m":"4569","flag":"updated","flag_detailed":"SPECIES_UPDATED"},{"lat":14.6333,"lng":-88.1333,"id":"gbif_476669978","taxonomy_updated_species":"Metlapilcoatlus_nummifer","final_species":"Metlapilcoatlus_mexicanus","accuracy_m":"3036","flag":"updated","flag_detailed":"POTENTIAL_DUBIOUS_RECORD; DISTRIBUTION_ERROR; POINT_OUTSIDE_DISTRIBUTION; SPECIES_UPDATED; ADDITIONAL_CHECKS_NEEDED"},{"lat":14.6333,"lng":-88.1333,"id":"gbif_476669979","taxonomy_updated_species":"Metlapilcoatlus_nummifer","final_species":"Metlapilcoatlus_mexicanus","accuracy_m":"3036","flag":"updated","flag_detailed":"POTENTIAL_DUBIOUS_RECORD; DISTRIBUTION_ERROR; POINT_OUTSIDE_DISTRIBUTION; SPECIES_UPDATED; ADDITIONAL_CHECKS_NEEDED"},{"lat":14.6333,"lng":-88.1333,"id":"gbif_476669980","taxonomy_updated_species":"Metlapilcoatlus_nummifer","final_species":"Metlapilcoatlus_mexicanus","accuracy_m":"3036","flag":"updated","flag_detailed":"POTENTIAL_DUBIOUS_RECORD; DISTRIBUTION_ERROR; POINT_OUTSIDE_DISTRIBUTION; SPECIES_UPDATED; ADDITIONAL_CHECKS_NEEDED"},{"lat":14.6333,"lng":-88.1333,"id":"gbif_476669981","taxonomy_updated_species":"Metlapilcoatlus_nummifer","final_species":"Metlapilcoatlus_mexicanus","accuracy_m":"3036","flag":"updated","flag_detailed":"POTENTIAL_DUBIOUS_RECORD; DISTRIBUTION_ERROR; POINT_OUTSIDE_DISTRIBUTION; SPECIES_UPDATED; ADDITIONAL_CHECKS_NEEDED"},{"lat":15,"lng":-86.5,"id":"gbif_476676343","taxonomy_updated_species":"Metlapilcoatlus_mexicanus","final_species":"Metlapilcoatlus_mexicanus","accuracy_m":"301","flag":"","flag_detailed":""},{"lat":14.6333,"lng":-88.1333,"id":"gbif_476678727","taxonomy_updated_species":"Metlapilcoatlus_nummifer","final_species":"Metlapilcoatlus_mexicanus","accuracy_m":"3036","flag":"updated","flag_detailed":"POTENTIAL_DUBIOUS_RECORD; DISTRIBUTION_ERROR; POINT_OUTSIDE_DISTRIBUTION; SPECIES_UPDATED; ADDITIONAL_CHECKS_NEEDED"},{"lat":15.7,"lng":-87.467,"id":"gbif_476681397","taxonomy_updated_species":"Metlapilcoatlus_mexicanus","final_species":"Metlapilcoatlus_mexicanus","accuracy_m":"3568","flag":"","flag_detailed":""},{"lat":15.7,"lng":-87.467,"id":"gbif_476681398","taxonomy_updated_species":"Metlapilcoatlus_mexicanus","final_species":"Metlapilcoatlus_mexicanus","accuracy_m":"3568","flag":"","flag_detailed":""},{"lat":15.7,"lng":-87.467,"id":"gbif_476681399","taxonomy_updated_species":"Metlapilcoatlus_mexicanus","final_species":"Metlapilcoatlus_mexicanus","accuracy_m":"3568","flag":"","flag_detailed":""},{"lat":15.7,"lng":-87.467,"id":"gbif_476681400","taxonomy_updated_species":"Metlapilcoatlus_mexicanus","final_species":"Metlapilcoatlus_mexicanus","accuracy_m":"3568","flag":"","flag_detailed":""},{"lat":10,"lng":-84,"id":"gbif_476682220","taxonomy_updated_species":"Metlapilcoatlus_mexicanus","final_species":"Metlapilcoatlus_mexicanus","accuracy_m":"301","flag":"","flag_detailed":""},{"lat":15.7833,"lng":-87.45,"id":"gbif_476682714","taxonomy_updated_species":"Metlapilcoatlus_mexicanus","final_species":"Metlapilcoatlus_mexicanus","accuracy_m":"4567","flag":"","flag_detailed":""},{"lat":15.1333,"lng":-87.3167,"id":"gbif_476688177","taxonomy_updated_species":"Metlapilcoatlus_nummifer","final_species":"Metlapilcoatlus_mexicanus","accuracy_m":"6069","flag":"updated","flag_detailed":"SPECIES_UPDATED"},{"lat":15.5,"lng":-88,"id":"gbif_476731191","taxonomy_updated_species":"Metlapilcoatlus_mexicanus","final_species":"Metlapilcoatlus_mexicanus","accuracy_m":"301","flag":"","flag_detailed":""},{"lat":17.1861,"lng":-89.0019,"id":"gbif_476790301","taxonomy_updated_species":"Metlapilcoatlus_nummifer","final_species":"Metlapilcoatlus_mexicanus","accuracy_m":"540","flag":"updated","flag_detailed":"SPECIES_UPDATED"},{"lat":15.7,"lng":-87.467,"id":"gbif_476790834","taxonomy_updated_species":"Metlapilcoatlus_mexicanus","final_species":"Metlapilcoatlus_mexicanus","accuracy_m":"3568","flag":"","flag_detailed":""},{"lat":15.4,"lng":-88.15,"id":"gbif_476797256","taxonomy_updated_species":"Metlapilcoatlus_nummifer","final_species":"Metlapilcoatlus_mexicanus","accuracy_m":"4569","flag":"updated","flag_detailed":"SPECIES_UPDATED"},{"lat":15.75,"lng":-90.25,"id":"gbif_621069429","taxonomy_updated_species":"Metlapilcoatlus_nummifer","final_species":"Metlapilcoatlus_mexicanus","accuracy_m":"272837","flag":"updated","flag_detailed":"SPECIES_UPDATED"},{"lat":8.782,"lng":-82.9481,"id":"gbif_657456635","taxonomy_updated_species":"Metlapilcoatlus_nummifer","final_species":"Metlapilcoatlus_mexicanus","accuracy_m":"3350","flag":"updated","flag_detailed":"SPECIES_UPDATED"},{"lat":10.2167,"lng":-83.6833,"id":"gbif_657496938","taxonomy_updated_species":"Metlapilcoatlus_nummifer","final_species":"Metlapilcoatlus_mexicanus","accuracy_m":"3595","flag":"updated","flag_detailed":"SPECIES_UPDATED"},{"lat":10.35,"lng":-84.4167,"id":"gbif_657496939","taxonomy_updated_species":"Metlapilcoatlus_nummifer","final_species":"Metlapilcoatlus_mexicanus","accuracy_m":"3196","flag":"updated","flag_detailed":"SPECIES_UPDATED"},{"lat":10.3667,"lng":-84.55,"id":"gbif_657496944","taxonomy_updated_species":"Metlapilcoatlus_nummifer","final_species":"Metlapilcoatlus_mexicanus","accuracy_m":"2944","flag":"updated","flag_detailed":"SPECIES_UPDATED"},{"lat":8.9486,"lng":-82.8647,"id":"gbif_657496945","taxonomy_updated_species":"Metlapilcoatlus_nummifer","final_species":"Metlapilcoatlus_mexicanus","accuracy_m":"4949","flag":"updated","flag_detailed":"SPECIES_UPDATED"},{"lat":10.3333,"lng":-84.4333,"id":"gbif_657496946","taxonomy_updated_species":"Metlapilcoatlus_nummifer","final_species":"Metlapilcoatlus_mexicanus","accuracy_m":"3594","flag":"updated","flag_detailed":"SPECIES_UPDATED"},{"lat":9.3833,"lng":-83.7,"id":"gbif_657496949","taxonomy_updated_species":"Metlapilcoatlus_nummifer","final_species":"Metlapilcoatlus_mexicanus","accuracy_m":"4096","flag":"updated","flag_detailed":"SPECIES_UPDATED"},{"lat":10.3667,"lng":-84.6167,"id":"gbif_657496950","taxonomy_updated_species":"Metlapilcoatlus_nummifer","final_species":"Metlapilcoatlus_mexicanus","accuracy_m":"3044","flag":"updated","flag_detailed":"SPECIES_UPDATED"},{"lat":10.3667,"lng":-84.6167,"id":"gbif_657496951","taxonomy_updated_species":"Metlapilcoatlus_nummifer","final_species":"Metlapilcoatlus_mexicanus","accuracy_m":"3044","flag":"updated","flag_detailed":"SPECIES_UPDATED"},{"lat":15.4,"lng":-88.15,"id":"gbif_894750880","taxonomy_updated_species":"Metlapilcoatlus_nummifer","final_species":"Metlapilcoatlus_mexicanus","accuracy_m":"4569","flag":"updated","flag_detailed":"SPECIES_UPDATED"},{"lat":15.4,"lng":-88.15,"id":"gbif_894750898","taxonomy_updated_species":"Metlapilcoatlus_nummifer","final_species":"Metlapilcoatlus_mexicanus","accuracy_m":"4569","flag":"updated","flag_detailed":"SPECIES_UPDATED"},{"lat":10.2632,"lng":-84.4052,"id":"gbif_991889437","taxonomy_updated_species":"Metlapilcoatlus_nummifer","final_species":"Metlapilcoatlus_mexicanus","accuracy_m":"NA","flag":"updated","flag_detailed":"SPECIES_UPDATED"},{"lat":10.2632,"lng":-84.4052,"id":"gbif_991889438","taxonomy_updated_species":"Metlapilcoatlus_nummifer","final_species":"Metlapilcoatlus_mexicanus","accuracy_m":"NA","flag":"updated","flag_detailed":"SPECIES_UPDATED"},{"lat":10.2632,"lng":-84.4052,"id":"gbif_991889439","taxonomy_updated_species":"Metlapilcoatlus_nummifer","final_species":"Metlapilcoatlus_mexicanus","accuracy_m":"NA","flag":"updated","flag_detailed":"SPECIES_UPDATED"},{"lat":16.37,"lng":-91.85,"id":"GJV07225","taxonomy_updated_species":"Metlapilcoatlus_mexicanus","final_species":"Metlapilcoatlus_mexicanus","accuracy_m":"NA","flag":"","flag_detailed":""},{"lat":16.8433,"lng":-91.5444,"id":"GJV07226","taxonomy_updated_species":"Metlapilcoatlus_mexicanus","final_species":"Metlapilcoatlus_mexicanus","accuracy_m":"NA","flag":"","flag_detailed":""},{"lat":16.8944,"lng":-91.7597,"id":"GJV07227","taxonomy_updated_species":"Metlapilcoatlus_mexicanus","final_species":"Metlapilcoatlus_mexicanus","accuracy_m":"NA","flag":"","flag_detailed":""},{"lat":17.11,"lng":-92.87,"id":"GJV07228","taxonomy_updated_species":"Metlapilcoatlus_mexicanus","final_species":"Metlapilcoatlus_mexicanus","accuracy_m":"NA","flag":"","flag_detailed":""},{"lat":17.2,"lng":-92.9667,"id":"GJV07229","taxonomy_updated_species":"Metlapilcoatlus_mexicanus","final_species":"Metlapilcoatlus_mexicanus","accuracy_m":"NA","flag":"","flag_detailed":""},{"lat":17.4278,"lng":-93.0306,"id":"GJV07230","taxonomy_updated_species":"Metlapilcoatlus_mexicanus","final_species":"Metlapilcoatlus_mexicanus","accuracy_m":"NA","flag":"","flag_detailed":""},{"lat":17.5467,"lng":-92.9533,"id":"GJV07231","taxonomy_updated_species":"Metlapilcoatlus_mexicanus","final_species":"Metlapilcoatlus_mexicanus","accuracy_m":"NA","flag":"","flag_detailed":""},{"lat":8.7826,"lng":-82.9463,"id":"GJV07232","taxonomy_updated_species":"Metlapilcoatlus_mexicanus","final_species":"Metlapilcoatlus_mexicanus","accuracy_m":"NA","flag":"","flag_detailed":""},{"lat":8.7826,"lng":-82.9463,"id":"GJV07233","taxonomy_updated_species":"Metlapilcoatlus_mexicanus","final_species":"Metlapilcoatlus_mexicanus","accuracy_m":"NA","flag":"","flag_detailed":""},{"lat":8.8333,"lng":-82.9667,"id":"GJV07234","taxonomy_updated_species":"Metlapilcoatlus_mexicanus","final_species":"Metlapilcoatlus_mexicanus","accuracy_m":"NA","flag":"","flag_detailed":""},{"lat":8.9493,"lng":-82.863,"id":"GJV07235","taxonomy_updated_species":"Metlapilcoatlus_mexicanus","final_species":"Metlapilcoatlus_mexicanus","accuracy_m":"NA","flag":"","flag_detailed":""},{"lat":9.0826,"lng":-83.0796,"id":"GJV07236","taxonomy_updated_species":"Metlapilcoatlus_mexicanus","final_species":"Metlapilcoatlus_mexicanus","accuracy_m":"NA","flag":"","flag_detailed":""},{"lat":9.3833,"lng":-83.7,"id":"GJV07237","taxonomy_updated_species":"Metlapilcoatlus_mexicanus","final_species":"Metlapilcoatlus_mexicanus","accuracy_m":"NA","flag":"","flag_detailed":""},{"lat":9.95,"lng":-83.6167,"id":"GJV07238","taxonomy_updated_species":"Metlapilcoatlus_mexicanus","final_species":"Metlapilcoatlus_mexicanus","accuracy_m":"NA","flag":"","flag_detailed":""},{"lat":10.2167,"lng":-83.6833,"id":"GJV07239","taxonomy_updated_species":"Metlapilcoatlus_mexicanus","final_species":"Metlapilcoatlus_mexicanus","accuracy_m":"NA","flag":"","flag_detailed":""},{"lat":10.2592,"lng":-84.0785,"id":"GJV07240","taxonomy_updated_species":"Metlapilcoatlus_mexicanus","final_species":"Metlapilcoatlus_mexicanus","accuracy_m":"NA","flag":"","flag_detailed":""},{"lat":10.2632,"lng":-84.4052,"id":"GJV07241","taxonomy_updated_species":"Metlapilcoatlus_mexicanus","final_species":"Metlapilcoatlus_mexicanus","accuracy_m":"NA","flag":"","flag_detailed":""},{"lat":10.3333,"lng":-84.4333,"id":"GJV07242","taxonomy_updated_species":"Metlapilcoatlus_mexicanus","final_species":"Metlapilcoatlus_mexicanus","accuracy_m":"NA","flag":"","flag_detailed":""},{"lat":10.35,"lng":-84.4167,"id":"GJV07243","taxonomy_updated_species":"Metlapilcoatlus_mexicanus","final_species":"Metlapilcoatlus_mexicanus","accuracy_m":"NA","flag":"","flag_detailed":""},{"lat":10.3667,"lng":-84.55,"id":"GJV07244","taxonomy_updated_species":"Metlapilcoatlus_mexicanus","final_species":"Metlapilcoatlus_mexicanus","accuracy_m":"NA","flag":"","flag_detailed":""},{"lat":10.3667,"lng":-84.6167,"id":"GJV07245","taxonomy_updated_species":"Metlapilcoatlus_mexicanus","final_species":"Metlapilcoatlus_mexicanus","accuracy_m":"NA","flag":"","flag_detailed":""},{"lat":10.5,"lng":-84.5,"id":"GJV07246","taxonomy_updated_species":"Metlapilcoatlus_mexicanus","final_species":"Metlapilcoatlus_mexicanus","accuracy_m":"NA","flag":"","flag_detailed":""},{"lat":10.6167,"lng":-85.0833,"id":"GJV07247","taxonomy_updated_species":"Metlapilcoatlus_mexicanus","final_species":"Metlapilcoatlus_mexicanus","accuracy_m":"NA","flag":"","flag_detailed":""},{"lat":10.7333,"lng":-85.1,"id":"GJV07248","taxonomy_updated_species":"Metlapilcoatlus_mexicanus","final_species":"Metlapilcoatlus_mexicanus","accuracy_m":"NA","flag":"","flag_detailed":""},{"lat":14.9167,"lng":-88.2333,"id":"GJV07249","taxonomy_updated_species":"Metlapilcoatlus_mexicanus","final_species":"Metlapilcoatlus_mexicanus","accuracy_m":"NA","flag":"","flag_detailed":""},{"lat":15.1167,"lng":-88.9333,"id":"GJV07250","taxonomy_updated_species":"Metlapilcoatlus_mexicanus","final_species":"Metlapilcoatlus_mexicanus","accuracy_m":"NA","flag":"","flag_detailed":""},{"lat":15.13,"lng":-88.9,"id":"GJV07251","taxonomy_updated_species":"Metlapilcoatlus_mexicanus","final_species":"Metlapilcoatlus_mexicanus","accuracy_m":"NA","flag":"","flag_detailed":""},{"lat":15.4,"lng":-88.15,"id":"GJV07252","taxonomy_updated_species":"Metlapilcoatlus_mexicanus","final_species":"Metlapilcoatlus_mexicanus","accuracy_m":"NA","flag":"","flag_detailed":""},{"lat":15.5,"lng":-88.0333,"id":"GJV07253","taxonomy_updated_species":"Metlapilcoatlus_mexicanus","final_species":"Metlapilcoatlus_mexicanus","accuracy_m":"NA","flag":"","flag_detailed":""},{"lat":15.5,"lng":-88.03,"id":"GJV07254","taxonomy_updated_species":"Metlapilcoatlus_mexicanus","final_species":"Metlapilcoatlus_mexicanus","accuracy_m":"NA","flag":"","flag_detailed":""},{"lat":15.5147,"lng":-87.4515,"id":"GJV07255","taxonomy_updated_species":"Metlapilcoatlus_mexicanus","final_species":"Metlapilcoatlus_mexicanus","accuracy_m":"NA","flag":"","flag_detailed":""},{"lat":15.52,"lng":-88.2,"id":"GJV07256","taxonomy_updated_species":"Metlapilcoatlus_mexicanus","final_species":"Metlapilcoatlus_mexicanus","accuracy_m":"NA","flag":"","flag_detailed":""},{"lat":15.5302,"lng":-87.2939,"id":"GJV07257","taxonomy_updated_species":"Metlapilcoatlus_mexicanus","final_species":"Metlapilcoatlus_mexicanus","accuracy_m":"NA","flag":"","flag_detailed":""},{"lat":15.7,"lng":-87.467,"id":"GJV07258","taxonomy_updated_species":"Metlapilcoatlus_mexicanus","final_species":"Metlapilcoatlus_mexicanus","accuracy_m":"NA","flag":"","flag_detailed":""},{"lat":15.7,"lng":-87.4667,"id":"GJV07259","taxonomy_updated_species":"Metlapilcoatlus_mexicanus","final_species":"Metlapilcoatlus_mexicanus","accuracy_m":"NA","flag":"","flag_detailed":""},{"lat":15.7169,"lng":-87.4642,"id":"GJV07260","taxonomy_updated_species":"Metlapilcoatlus_mexicanus","final_species":"Metlapilcoatlus_mexicanus","accuracy_m":"NA","flag":"","flag_detailed":""},{"lat":15.7833,"lng":-87.45,"id":"GJV07261","taxonomy_updated_species":"Metlapilcoatlus_mexicanus","final_species":"Metlapilcoatlus_mexicanus","accuracy_m":"NA","flag":"","flag_detailed":""},{"lat":16.098,"lng":-91.694,"id":"GJV07262","taxonomy_updated_species":"Metlapilcoatlus_mexicanus","final_species":"Metlapilcoatlus_mexicanus","accuracy_m":"NA","flag":"","flag_detailed":""},{"lat":16.122,"lng":-91.708,"id":"GJV07263","taxonomy_updated_species":"Metlapilcoatlus_mexicanus","final_species":"Metlapilcoatlus_mexicanus","accuracy_m":"NA","flag":"","flag_detailed":""},{"lat":16.2508,"lng":-92.1333,"id":"GJV07264","taxonomy_updated_species":"Metlapilcoatlus_mexicanus","final_species":"Metlapilcoatlus_mexicanus","accuracy_m":"NA","flag":"","flag_detailed":""},{"lat":16.251,"lng":-92.134,"id":"GJV07265","taxonomy_updated_species":"Metlapilcoatlus_mexicanus","final_species":"Metlapilcoatlus_mexicanus","accuracy_m":"NA","flag":"","flag_detailed":""},{"lat":16.333,"lng":-89.133,"id":"GJV07266","taxonomy_updated_species":"Metlapilcoatlus_mexicanus","final_species":"Metlapilcoatlus_mexicanus","accuracy_m":"NA","flag":"","flag_detailed":""},{"lat":16.3333,"lng":-88.9833,"id":"GJV07267","taxonomy_updated_species":"Metlapilcoatlus_mexicanus","final_species":"Metlapilcoatlus_mexicanus","accuracy_m":"NA","flag":"","flag_detailed":""},{"lat":16.489,"lng":-92.233,"id":"GJV07268","taxonomy_updated_species":"Metlapilcoatlus_mexicanus","final_species":"Metlapilcoatlus_mexicanus","accuracy_m":"NA","flag":"","flag_detailed":""},{"lat":16.649,"lng":-92.544,"id":"GJV07269","taxonomy_updated_species":"Metlapilcoatlus_mexicanus","final_species":"Metlapilcoatlus_mexicanus","accuracy_m":"NA","flag":"","flag_detailed":""},{"lat":16.6666,"lng":-92.5427,"id":"GJV07270","taxonomy_updated_species":"Metlapilcoatlus_mexicanus","final_species":"Metlapilcoatlus_mexicanus","accuracy_m":"NA","flag":"","flag_detailed":""},{"lat":16.729,"lng":-92.719,"id":"GJV07271","taxonomy_updated_species":"Metlapilcoatlus_mexicanus","final_species":"Metlapilcoatlus_mexicanus","accuracy_m":"NA","flag":"","flag_detailed":""},{"lat":16.9074,"lng":-92.0933,"id":"GJV07272","taxonomy_updated_species":"Metlapilcoatlus_mexicanus","final_species":"Metlapilcoatlus_mexicanus","accuracy_m":"NA","flag":"","flag_detailed":""},{"lat":17.1107,"lng":-92.8699,"id":"GJV07273","taxonomy_updated_species":"Metlapilcoatlus_mexicanus","final_species":"Metlapilcoatlus_mexicanus","accuracy_m":"NA","flag":"","flag_detailed":""},{"lat":17.159,"lng":-92.899,"id":"GJV07274","taxonomy_updated_species":"Metlapilcoatlus_mexicanus","final_species":"Metlapilcoatlus_mexicanus","accuracy_m":"NA","flag":"","flag_detailed":""},{"lat":17.1861,"lng":-89.0019,"id":"GJV07275","taxonomy_updated_species":"Metlapilcoatlus_mexicanus","final_species":"Metlapilcoatlus_mexicanus","accuracy_m":"NA","flag":"","flag_detailed":""},{"lat":8.7998,"lng":-82.9554,"id":"LIAP0245","taxonomy_updated_species":"Metlapilcoatlus_mexicanus","final_species":"Metlapilcoatlus_mexicanus","accuracy_m":"1000","flag":"","flag_detailed":""},{"lat":15.5,"lng":-88.9167,"id":"Martins00016","taxonomy_updated_species":"Metlapilcoatlus_mexicanus","final_species":"Metlapilcoatlus_mexicanus","accuracy_m":"NA","flag":"","flag_detailed":""},{"lat":8.7787,"lng":-80.1437,"id":"Martins00200","taxonomy_updated_species":"Metlapilcoatlus_mexicanus","final_species":"Metlapilcoatlus_mexicanus","accuracy_m":"NA","flag":"dubious","flag_detailed":"POTENTIAL_DUBIOUS_RECORD; DISTRIBUTION_ERROR; POINT_OUTSIDE_DISTRIBUTION; DISTANCE_EXCEEDS_50KM; UNCERTAIN_SPECIES_ID; ADDITIONAL_CHECKS_NEEDED"},{"lat":17.0667,"lng":-92.8604,"id":"Martins00322","taxonomy_updated_species":"Metlapilcoatlus_nummifer","final_species":"Metlapilcoatlus_mexicanus","accuracy_m":"NA","flag":"updated","flag_detailed":"SPECIES_UPDATED"},{"lat":17.0667,"lng":-92.8604,"id":"Martins00323","taxonomy_updated_species":"Metlapilcoatlus_nummifer","final_species":"Metlapilcoatlus_mexicanus","accuracy_m":"NA","flag":"updated","flag_detailed":"SPECIES_UPDATED"},{"lat":16.3333,"lng":-88.9833,"id":"Martins00583","taxonomy_updated_species":"Metlapilcoatlus_nummifer","final_species":"Metlapilcoatlus_mexicanus","accuracy_m":"NA","flag":"updated","flag_detailed":"SPECIES_UPDATED"},{"lat":16.3333,"lng":-88.9833,"id":"Martins00584","taxonomy_updated_species":"Metlapilcoatlus_nummifer","final_species":"Metlapilcoatlus_mexicanus","accuracy_m":"NA","flag":"updated","flag_detailed":"SPECIES_UPDATED"},{"lat":15.4168,"lng":-88.1633,"id":"Martins00785","taxonomy_updated_species":"Metlapilcoatlus_mexicanus","final_species":"Metlapilcoatlus_mexicanus","accuracy_m":"NA","flag":"","flag_detailed":""},{"lat":15.2667,"lng":-87.3167,"id":"Martins00786","taxonomy_updated_species":"Metlapilcoatlus_mexicanus","final_species":"Metlapilcoatlus_mexicanus","accuracy_m":"NA","flag":"","flag_detailed":""},{"lat":15.9489,"lng":-90.1175,"id":"Martins00787","taxonomy_updated_species":"Metlapilcoatlus_mexicanus","final_species":"Metlapilcoatlus_mexicanus","accuracy_m":"NA","flag":"","flag_detailed":""},{"lat":8.8218,"lng":-82.9721,"id":"Martins02091","taxonomy_updated_species":"Metlapilcoatlus_nummifer","final_species":"Metlapilcoatlus_mexicanus","accuracy_m":"NA","flag":"updated","flag_detailed":"SPECIES_UPDATED"},{"lat":8.8218,"lng":-82.9721,"id":"Martins02092","taxonomy_updated_species":"Metlapilcoatlus_nummifer","final_species":"Metlapilcoatlus_mexicanus","accuracy_m":"NA","flag":"updated","flag_detailed":"SPECIES_UPDATED"},{"lat":10.3667,"lng":-84.55,"id":"Martins02093","taxonomy_updated_species":"Metlapilcoatlus_nummifer","final_species":"Metlapilcoatlus_mexicanus","accuracy_m":"NA","flag":"updated","flag_detailed":"SPECIES_UPDATED"},{"lat":10.3667,"lng":-84.55,"id":"Martins02094","taxonomy_updated_species":"Metlapilcoatlus_nummifer","final_species":"Metlapilcoatlus_mexicanus","accuracy_m":"NA","flag":"updated","flag_detailed":"SPECIES_UPDATED"},{"lat":8.95,"lng":-82.8667,"id":"Martins02095","taxonomy_updated_species":"Metlapilcoatlus_nummifer","final_species":"Metlapilcoatlus_mexicanus","accuracy_m":"NA","flag":"updated","flag_detailed":"SPECIES_UPDATED"},{"lat":8.95,"lng":-82.8667,"id":"Martins02096","taxonomy_updated_species":"Metlapilcoatlus_nummifer","final_species":"Metlapilcoatlus_mexicanus","accuracy_m":"NA","flag":"updated","flag_detailed":"SPECIES_UPDATED"},{"lat":10.3667,"lng":-84.6167,"id":"Martins02097","taxonomy_updated_species":"Metlapilcoatlus_nummifer","final_species":"Metlapilcoatlus_mexicanus","accuracy_m":"NA","flag":"updated","flag_detailed":"SPECIES_UPDATED"},{"lat":10.3667,"lng":-84.6167,"id":"Martins02098","taxonomy_updated_species":"Metlapilcoatlus_nummifer","final_species":"Metlapilcoatlus_mexicanus","accuracy_m":"NA","flag":"updated","flag_detailed":"SPECIES_UPDATED"},{"lat":8.7833,"lng":-82.95,"id":"Martins02127","taxonomy_updated_species":"Metlapilcoatlus_nummifer","final_species":"Metlapilcoatlus_mexicanus","accuracy_m":"NA","flag":"updated","flag_detailed":"SPECIES_UPDATED"},{"lat":8.7833,"lng":-82.95,"id":"Martins02128","taxonomy_updated_species":"Metlapilcoatlus_nummifer","final_species":"Metlapilcoatlus_mexicanus","accuracy_m":"NA","flag":"updated","flag_detailed":"SPECIES_UPDATED"},{"lat":10.2167,"lng":-83.6833,"id":"Martins02189","taxonomy_updated_species":"Metlapilcoatlus_nummifer","final_species":"Metlapilcoatlus_mexicanus","accuracy_m":"NA","flag":"updated","flag_detailed":"SPECIES_UPDATED"},{"lat":10.2167,"lng":-83.6833,"id":"Martins02190","taxonomy_updated_species":"Metlapilcoatlus_nummifer","final_species":"Metlapilcoatlus_mexicanus","accuracy_m":"NA","flag":"updated","flag_detailed":"SPECIES_UPDATED"},{"lat":10.35,"lng":-84.4167,"id":"Martins02191","taxonomy_updated_species":"Metlapilcoatlus_nummifer","final_species":"Metlapilcoatlus_mexicanus","accuracy_m":"NA","flag":"updated","flag_detailed":"SPECIES_UPDATED"},{"lat":10.35,"lng":-84.4167,"id":"Martins02192","taxonomy_updated_species":"Metlapilcoatlus_nummifer","final_species":"Metlapilcoatlus_mexicanus","accuracy_m":"NA","flag":"updated","flag_detailed":"SPECIES_UPDATED"},{"lat":8.7833,"lng":-82.95,"id":"Martins02193","taxonomy_updated_species":"Metlapilcoatlus_nummifer","final_species":"Metlapilcoatlus_mexicanus","accuracy_m":"NA","flag":"updated","flag_detailed":"SPECIES_UPDATED"},{"lat":8.7833,"lng":-82.95,"id":"Martins02194","taxonomy_updated_species":"Metlapilcoatlus_nummifer","final_species":"Metlapilcoatlus_mexicanus","accuracy_m":"NA","flag":"updated","flag_detailed":"SPECIES_UPDATED"},{"lat":10.7114,"lng":-84.8153,"id":"Martins02195","taxonomy_updated_species":"Metlapilcoatlus_nummifer","final_species":"Metlapilcoatlus_mexicanus","accuracy_m":"NA","flag":"updated","flag_detailed":"SPECIES_UPDATED"},{"lat":10.7114,"lng":-84.8153,"id":"Martins02196","taxonomy_updated_species":"Metlapilcoatlus_nummifer","final_species":"Metlapilcoatlus_mexicanus","accuracy_m":"NA","flag":"updated","flag_detailed":"SPECIES_UPDATED"},{"lat":9.0833,"lng":-83.0833,"id":"Martins02197","taxonomy_updated_species":"Metlapilcoatlus_nummifer","final_species":"Metlapilcoatlus_mexicanus","accuracy_m":"NA","flag":"updated","flag_detailed":"SPECIES_UPDATED"},{"lat":9.0833,"lng":-83.0833,"id":"Martins02198","taxonomy_updated_species":"Metlapilcoatlus_nummifer","final_species":"Metlapilcoatlus_mexicanus","accuracy_m":"NA","flag":"updated","flag_detailed":"SPECIES_UPDATED"},{"lat":10.321,"lng":-84.4287,"id":"Martins02199","taxonomy_updated_species":"Metlapilcoatlus_nummifer","final_species":"Metlapilcoatlus_mexicanus","accuracy_m":"NA","flag":"updated","flag_detailed":"SPECIES_UPDATED"},{"lat":10.321,"lng":-84.4287,"id":"Martins02200","taxonomy_updated_species":"Metlapilcoatlus_nummifer","final_species":"Metlapilcoatlus_mexicanus","accuracy_m":"NA","flag":"updated","flag_detailed":"SPECIES_UPDATED"},{"lat":10.7333,"lng":-85.1,"id":"Martins02201","taxonomy_updated_species":"Metlapilcoatlus_nummifer","final_species":"Metlapilcoatlus_mexicanus","accuracy_m":"NA","flag":"updated","flag_detailed":"SPECIES_UPDATED"},{"lat":10.7333,"lng":-85.1,"id":"Martins02202","taxonomy_updated_species":"Metlapilcoatlus_nummifer","final_species":"Metlapilcoatlus_mexicanus","accuracy_m":"NA","flag":"updated","flag_detailed":"SPECIES_UPDATED"},{"lat":9.3833,"lng":-83.7,"id":"Martins02203","taxonomy_updated_species":"Metlapilcoatlus_nummifer","final_species":"Metlapilcoatlus_mexicanus","accuracy_m":"NA","flag":"updated","flag_detailed":"SPECIES_UPDATED"},{"lat":9.3833,"lng":-83.7,"id":"Martins02204","taxonomy_updated_species":"Metlapilcoatlus_nummifer","final_species":"Metlapilcoatlus_mexicanus","accuracy_m":"NA","flag":"updated","flag_detailed":"SPECIES_UPDATED"},{"lat":16.6658,"lng":-92.5428,"id":"Martins03538","taxonomy_updated_species":"Metlapilcoatlus_nummifer","final_species":"Metlapilcoatlus_mexicanus","accuracy_m":"NA","flag":"updated","flag_detailed":"SPECIES_UPDATED"},{"lat":16.6658,"lng":-92.5428,"id":"Martins03539","taxonomy_updated_species":"Metlapilcoatlus_nummifer","final_species":"Metlapilcoatlus_mexicanus","accuracy_m":"NA","flag":"updated","flag_detailed":"SPECIES_UPDATED"},{"lat":10.087,"lng":-84.47,"id":"Martins03687","taxonomy_updated_species":"Metlapilcoatlus_nummifer","final_species":"Metlapilcoatlus_mexicanus","accuracy_m":"NA","flag":"updated","flag_detailed":"SPECIES_UPDATED"},{"lat":10.087,"lng":-84.47,"id":"Martins03688","taxonomy_updated_species":"Metlapilcoatlus_nummifer","final_species":"Metlapilcoatlus_mexicanus","accuracy_m":"NA","flag":"updated","flag_detailed":"SPECIES_UPDATED"},{"lat":8.9094,"lng":-82.9331,"id":"Martins03774","taxonomy_updated_species":"Metlapilcoatlus_nummifer","final_species":"Metlapilcoatlus_mexicanus","accuracy_m":"NA","flag":"updated","flag_detailed":"SPECIES_UPDATED"},{"lat":9.6525,"lng":-84.0213,"id":"Martins03783","taxonomy_updated_species":"Metlapilcoatlus_nummifer","final_species":"Metlapilcoatlus_mexicanus","accuracy_m":"NA","flag":"updated","flag_detailed":"SPECIES_UPDATED"},{"lat":9.9058,"lng":-83.6842,"id":"Martins03790","taxonomy_updated_species":"Metlapilcoatlus_nummifer","final_species":"Metlapilcoatlus_mexicanus","accuracy_m":"NA","flag":"updated","flag_detailed":"SPECIES_UPDATED"},{"lat":17.5506,"lng":-92.9532,"id":"Martins05178","taxonomy_updated_species":"Metlapilcoatlus_mexicanus","final_species":"Metlapilcoatlus_mexicanus","accuracy_m":"NA","flag":"","flag_detailed":""},{"lat":16.7378,"lng":-92.6369,"id":"Martins05179","taxonomy_updated_species":"Metlapilcoatlus_mexicanus","final_species":"Metlapilcoatlus_mexicanus","accuracy_m":"NA","flag":"","flag_detailed":""},{"lat":15.471,"lng":-90.3716,"id":"Martins05180","taxonomy_updated_species":"Metlapilcoatlus_mexicanus","final_species":"Metlapilcoatlus_mexicanus","accuracy_m":"NA","flag":"","flag_detailed":""},{"lat":16.7834,"lng":-90.1168,"id":"Martins05181","taxonomy_updated_species":"Metlapilcoatlus_mexicanus","final_species":"Metlapilcoatlus_mexicanus","accuracy_m":"NA","flag":"","flag_detailed":""},{"lat":15.1335,"lng":-88.2333,"id":"Martins05182","taxonomy_updated_species":"Metlapilcoatlus_mexicanus","final_species":"Metlapilcoatlus_mexicanus","accuracy_m":"NA","flag":"","flag_detailed":""},{"lat":15.6867,"lng":-88.1678,"id":"Martins05183","taxonomy_updated_species":"Metlapilcoatlus_mexicanus","final_species":"Metlapilcoatlus_mexicanus","accuracy_m":"NA","flag":"","flag_detailed":""},{"lat":12.9208,"lng":-85.9178,"id":"Martins05184","taxonomy_updated_species":"Metlapilcoatlus_mexicanus","final_species":"Metlapilcoatlus_mexicanus","accuracy_m":"NA","flag":"dubious","flag_detailed":"POTENTIAL_DUBIOUS_RECORD; DISTRIBUTION_ERROR; POINT_OUTSIDE_DISTRIBUTION; DISTANCE_EXCEEDS_50KM; UNCERTAIN_SPECIES_ID; ADDITIONAL_CHECKS_NEEDED"},{"lat":9.7892,"lng":-84.1261,"id":"Martins05185","taxonomy_updated_species":"Metlapilcoatlus_mexicanus","final_species":"Metlapilcoatlus_mexicanus","accuracy_m":"NA","flag":"","flag_detailed":""},{"lat":10.2058,"lng":-83.7892,"id":"Martins05186","taxonomy_updated_species":"Metlapilcoatlus_mexicanus","final_species":"Metlapilcoatlus_mexicanus","accuracy_m":"NA","flag":"","flag_detailed":""},{"lat":9.9683,"lng":-83.6143,"id":"Martins05187","taxonomy_updated_species":"Metlapilcoatlus_mexicanus","final_species":"Metlapilcoatlus_mexicanus","accuracy_m":"NA","flag":"","flag_detailed":""},{"lat":9.9363,"lng":-83.5938,"id":"Martins05188","taxonomy_updated_species":"Metlapilcoatlus_mexicanus","final_species":"Metlapilcoatlus_mexicanus","accuracy_m":"NA","flag":"","flag_detailed":""},{"lat":10.0962,"lng":-83.5115,"id":"Martins05189","taxonomy_updated_species":"Metlapilcoatlus_mexicanus","final_species":"Metlapilcoatlus_mexicanus","accuracy_m":"NA","flag":"","flag_detailed":""},{"lat":8.8266,"lng":-82.974,"id":"Martins05190","taxonomy_updated_species":"Metlapilcoatlus_mexicanus","final_species":"Metlapilcoatlus_mexicanus","accuracy_m":"NA","flag":"","flag_detailed":""},{"lat":8.8218,"lng":-82.9722,"id":"Martins05191","taxonomy_updated_species":"Metlapilcoatlus_mexicanus","final_species":"Metlapilcoatlus_mexicanus","accuracy_m":"NA","flag":"","flag_detailed":""},{"lat":8.8218,"lng":-82.9722,"id":"Martins05192","taxonomy_updated_species":"Metlapilcoatlus_mexicanus","final_species":"Metlapilcoatlus_mexicanus","accuracy_m":"NA","flag":"","flag_detailed":""},{"lat":8.8218,"lng":-82.9721,"id":"Martins05193","taxonomy_updated_species":"Metlapilcoatlus_mexicanus","final_species":"Metlapilcoatlus_mexicanus","accuracy_m":"NA","flag":"","flag_detailed":""},{"lat":8.8298,"lng":-82.9695,"id":"Martins05194","taxonomy_updated_species":"Metlapilcoatlus_mexicanus","final_species":"Metlapilcoatlus_mexicanus","accuracy_m":"NA","flag":"","flag_detailed":""},{"lat":8.9092,"lng":-82.933,"id":"Martins05195","taxonomy_updated_species":"Metlapilcoatlus_mexicanus","final_species":"Metlapilcoatlus_mexicanus","accuracy_m":"NA","flag":"","flag_detailed":""},{"lat":15.9581,"lng":-90.1963,"id":"Martins05200","taxonomy_updated_species":"Metlapilcoatlus_nummifer","final_species":"Metlapilcoatlus_mexicanus","accuracy_m":"NA","flag":"updated","flag_detailed":"SPECIES_UPDATED"},{"lat":15.5653,"lng":-88.3145,"id":"Martins05201","taxonomy_updated_species":"Metlapilcoatlus_nummifer","final_species":"Metlapilcoatlus_mexicanus","accuracy_m":"NA","flag":"updated","flag_detailed":"SPECIES_UPDATED"},{"lat":10.7,"lng":-85.65,"id":"Martins05202","taxonomy_updated_species":"Metlapilcoatlus_nummifer","final_species":"Metlapilcoatlus_mexicanus","accuracy_m":"NA","flag":"updated","flag_detailed":"POTENTIAL_DUBIOUS_RECORD; DISTRIBUTION_ERROR; POINT_OUTSIDE_DISTRIBUTION; SPECIES_UPDATED; ADDITIONAL_CHECKS_NEEDED"},{"lat":10.85,"lng":-85.6167,"id":"Martins05203","taxonomy_updated_species":"Metlapilcoatlus_nummifer","final_species":"Metlapilcoatlus_mexicanus","accuracy_m":"NA","flag":"updated","flag_detailed":"POTENTIAL_DUBIOUS_RECORD; DISTRIBUTION_ERROR; POINT_OUTSIDE_DISTRIBUTION; SPECIES_UPDATED; ADDITIONAL_CHECKS_NEEDED"},{"lat":10.0868,"lng":-84.47,"id":"Martins05204","taxonomy_updated_species":"Metlapilcoatlus_nummifer","final_species":"Metlapilcoatlus_mexicanus","accuracy_m":"NA","flag":"updated","flag_detailed":"SPECIES_UPDATED"},{"lat":9.9058,"lng":-83.6842,"id":"Martins05205","taxonomy_updated_species":"Metlapilcoatlus_nummifer","final_species":"Metlapilcoatlus_mexicanus","accuracy_m":"NA","flag":"updated","flag_detailed":"SPECIES_UPDATED"},{"lat":15.4169,"lng":-88.1634,"id":"Martins08372","taxonomy_updated_species":"Metlapilcoatlus_nummifer","final_species":"Metlapilcoatlus_mexicanus","accuracy_m":"NA","flag":"updated","flag_detailed":"SPECIES_UPDATED"},{"lat":15.4169,"lng":-88.1634,"id":"Martins08373","taxonomy_updated_species":"Metlapilcoatlus_nummifer","final_species":"Metlapilcoatlus_mexicanus","accuracy_m":"NA","flag":"updated","flag_detailed":"SPECIES_UPDATED"},{"lat":17.4299,"lng":-93.0356,"id":"Martins08809","taxonomy_updated_species":"Metlapilcoatlus_nummifer","final_species":"Metlapilcoatlus_mexicanus","accuracy_m":"NA","flag":"updated","flag_detailed":"SPECIES_UPDATED"},{"lat":17.4299,"lng":-93.0356,"id":"Martins08810","taxonomy_updated_species":"Metlapilcoatlus_nummifer","final_species":"Metlapilcoatlus_mexicanus","accuracy_m":"NA","flag":"updated","flag_detailed":"SPECIES_UPDATED"},{"lat":16.2436,"lng":-92.1235,"id":"Martins08826","taxonomy_updated_species":"Metlapilcoatlus_nummifer","final_species":"Metlapilcoatlus_mexicanus","accuracy_m":"NA","flag":"updated","flag_detailed":"SPECIES_UPDATED"},{"lat":16.2436,"lng":-92.1235,"id":"Martins08827","taxonomy_updated_species":"Metlapilcoatlus_nummifer","final_species":"Metlapilcoatlus_mexicanus","accuracy_m":"NA","flag":"updated","flag_detailed":"SPECIES_UPDATED"},{"lat":15.5593,"lng":-88.6253,"id":"Martins08864","taxonomy_updated_species":"Metlapilcoatlus_nummifer","final_species":"Metlapilcoatlus_mexicanus","accuracy_m":"NA","flag":"updated","flag_detailed":"SPECIES_UPDATED"},{"lat":15.5593,"lng":-88.6253,"id":"Martins08865","taxonomy_updated_species":"Metlapilcoatlus_nummifer","final_species":"Metlapilcoatlus_mexicanus","accuracy_m":"NA","flag":"updated","flag_detailed":"SPECIES_UPDATED"},{"lat":15.4817,"lng":-88.2217,"id":"Martins08975","taxonomy_updated_species":"Metlapilcoatlus_mexicanus","final_species":"Metlapilcoatlus_mexicanus","accuracy_m":"NA","flag":"","flag_detailed":""},{"lat":15.5461,"lng":-88.1633,"id":"Martins08976","taxonomy_updated_species":"Metlapilcoatlus_mexicanus","final_species":"Metlapilcoatlus_mexicanus","accuracy_m":"NA","flag":"","flag_detailed":""},{"lat":17.1793,"lng":-91.2559,"id":"Martins09115","taxonomy_updated_species":"Metlapilcoatlus_mexicanus","final_species":"Metlapilcoatlus_mexicanus","accuracy_m":"NA","flag":"","flag_detailed":""},{"lat":17.1793,"lng":-91.2559,"id":"Martins09116","taxonomy_updated_species":"Metlapilcoatlus_mexicanus","final_species":"Metlapilcoatlus_mexicanus","accuracy_m":"NA","flag":"","flag_detailed":""},{"lat":17.1793,"lng":-91.2559,"id":"Martins09117","taxonomy_updated_species":"Metlapilcoatlus_mexicanus","final_species":"Metlapilcoatlus_mexicanus","accuracy_m":"NA","flag":"","flag_detailed":""},{"lat":15.7236,"lng":-92.1041,"id":"Martins09118","taxonomy_updated_species":"Metlapilcoatlus_mexicanus","final_species":"Metlapilcoatlus_mexicanus","accuracy_m":"NA","flag":"geoDist","flag_detailed":"POTENTIAL_DUBIOUS_RECORD; DISTRIBUTION_ERROR; POINT_OUTSIDE_DISTRIBUTION; ADDITIONAL_CHECKS_NEEDED"},{"lat":15.7236,"lng":-92.1041,"id":"Martins09119","taxonomy_updated_species":"Metlapilcoatlus_mexicanus","final_species":"Metlapilcoatlus_mexicanus","accuracy_m":"NA","flag":"geoDist","flag_detailed":"POTENTIAL_DUBIOUS_RECORD; DISTRIBUTION_ERROR; POINT_OUTSIDE_DISTRIBUTION; ADDITIONAL_CHECKS_NEEDED"},{"lat":17.2074,"lng":-90.2129,"id":"Martins09507","taxonomy_updated_species":"Metlapilcoatlus_nummifer","final_species":"Metlapilcoatlus_mexicanus","accuracy_m":"NA","flag":"updated","flag_detailed":"POTENTIAL_DUBIOUS_RECORD; DISTRIBUTION_ERROR; POINT_OUTSIDE_DISTRIBUTION; SPECIES_UPDATED; ADDITIONAL_CHECKS_NEEDED"},{"lat":17.2074,"lng":-90.2129,"id":"Martins09508","taxonomy_updated_species":"Metlapilcoatlus_nummifer","final_species":"Metlapilcoatlus_mexicanus","accuracy_m":"NA","flag":"updated","flag_detailed":"POTENTIAL_DUBIOUS_RECORD; DISTRIBUTION_ERROR; POINT_OUTSIDE_DISTRIBUTION; SPECIES_UPDATED; ADDITIONAL_CHECKS_NEEDED"},{"lat":15.517,"lng":-88.3046,"id":"Martins09753","taxonomy_updated_species":"Metlapilcoatlus_mexicanus","final_species":"Metlapilcoatlus_mexicanus","accuracy_m":"NA","flag":"","flag_detailed":""},{"lat":15.517,"lng":-88.3046,"id":"Martins09754","taxonomy_updated_species":"Metlapilcoatlus_mexicanus","final_species":"Metlapilcoatlus_mexicanus","accuracy_m":"NA","flag":"","flag_detailed":""},{"lat":15.5,"lng":-88.03,"id":"Martins09832","taxonomy_updated_species":"Metlapilcoatlus_nummifer","final_species":"Metlapilcoatlus_mexicanus","accuracy_m":"NA","flag":"updated","flag_detailed":"SPECIES_UPDATED"},{"lat":15.5,"lng":-88.03,"id":"Martins09833","taxonomy_updated_species":"Metlapilcoatlus_nummifer","final_species":"Metlapilcoatlus_mexicanus","accuracy_m":"NA","flag":"updated","flag_detailed":"SPECIES_UPDATED"},{"lat":15.7833,"lng":-87.45,"id":"Martins09839","taxonomy_updated_species":"Metlapilcoatlus_nummifer","final_species":"Metlapilcoatlus_mexicanus","accuracy_m":"NA","flag":"updated","flag_detailed":"SPECIES_UPDATED"},{"lat":15.7833,"lng":-87.45,"id":"Martins09840","taxonomy_updated_species":"Metlapilcoatlus_nummifer","final_species":"Metlapilcoatlus_mexicanus","accuracy_m":"NA","flag":"updated","flag_detailed":"SPECIES_UPDATED"},{"lat":15.6189,"lng":-86.8622,"id":"Martins09852","taxonomy_updated_species":"Metlapilcoatlus_mexicanus","final_species":"Metlapilcoatlus_mexicanus","accuracy_m":"NA","flag":"","flag_detailed":""},{"lat":15.6189,"lng":-86.8622,"id":"Martins09853","taxonomy_updated_species":"Metlapilcoatlus_mexicanus","final_species":"Metlapilcoatlus_mexicanus","accuracy_m":"NA","flag":"","flag_detailed":""},{"lat":15.4721,"lng":-88.8441,"id":"Martins09874","taxonomy_updated_species":"Metlapilcoatlus_mexicanus","final_species":"Metlapilcoatlus_mexicanus","accuracy_m":"NA","flag":"","flag_detailed":""},{"lat":9.9011,"lng":-83.6837,"id":"Martins09881","taxonomy_updated_species":"Metlapilcoatlus_mexicanus","final_species":"Metlapilcoatlus_mexicanus","accuracy_m":"NA","flag":"","flag_detailed":""},{"lat":9.9016,"lng":-83.6844,"id":"Martins09882","taxonomy_updated_species":"Metlapilcoatlus_mexicanus","final_species":"Metlapilcoatlus_mexicanus","accuracy_m":"NA","flag":"","flag_detailed":""},{"lat":15.6902,"lng":-88.6204,"id":"Martins09888","taxonomy_updated_species":"Metlapilcoatlus_mexicanus","final_species":"Metlapilcoatlus_mexicanus","accuracy_m":"NA","flag":"","flag_detailed":""},{"lat":15.4224,"lng":-89.0795,"id":"Martins09889","taxonomy_updated_species":"Metlapilcoatlus_mexicanus","final_species":"Metlapilcoatlus_mexicanus","accuracy_m":"NA","flag":"","flag_detailed":""},{"lat":15.4224,"lng":-89.0795,"id":"Martins09890","taxonomy_updated_species":"Metlapilcoatlus_mexicanus","final_species":"Metlapilcoatlus_mexicanus","accuracy_m":"NA","flag":"","flag_detailed":""},{"lat":9.8904,"lng":-84.3109,"id":"Martins09893","taxonomy_updated_species":"Metlapilcoatlus_olmec","final_species":"Metlapilcoatlus_mexicanus","accuracy_m":"NA","flag":"updated","flag_detailed":"SPECIES_UPDATED"},{"lat":15.167,"lng":-90.1501,"id":"Martins09909","taxonomy_updated_species":"Metlapilcoatlus_mexicanus","final_species":"Metlapilcoatlus_mexicanus","accuracy_m":"NA","flag":"","flag_detailed":""},{"lat":15.1667,"lng":-90.15,"id":"Martins09910","taxonomy_updated_species":"Metlapilcoatlus_mexicanus","final_species":"Metlapilcoatlus_mexicanus","accuracy_m":"NA","flag":"","flag_detailed":""},{"lat":15.667,"lng":-89.483,"id":"Martins09911","taxonomy_updated_species":"Metlapilcoatlus_mexicanus","final_species":"Metlapilcoatlus_mexicanus","accuracy_m":"NA","flag":"","flag_detailed":""},{"lat":15.6865,"lng":-88.6443,"id":"Martins09913","taxonomy_updated_species":"Metlapilcoatlus_mexicanus","final_species":"Metlapilcoatlus_mexicanus","accuracy_m":"NA","flag":"","flag_detailed":""},{"lat":10.1599,"lng":-83.9744,"id":"Martins09915","taxonomy_updated_species":"Metlapilcoatlus_olmec","final_species":"Metlapilcoatlus_mexicanus","accuracy_m":"NA","flag":"updated","flag_detailed":"SPECIES_UPDATED"},{"lat":10.4735,"lng":-84.0167,"id":"Martins09918","taxonomy_updated_species":"Metlapilcoatlus_olmec","final_species":"Metlapilcoatlus_mexicanus","accuracy_m":"NA","flag":"updated","flag_detailed":"POTENTIAL_DUBIOUS_RECORD; DISTRIBUTION_ERROR; POINT_OUTSIDE_DISTRIBUTION; SPECIES_UPDATED; ADDITIONAL_CHECKS_NEEDED"},{"lat":10.0962,"lng":-83.5115,"id":"Martins09921","taxonomy_updated_species":"Metlapilcoatlus_mexicanus","final_species":"Metlapilcoatlus_mexicanus","accuracy_m":"NA","flag":"","flag_detailed":""},{"lat":10.0962,"lng":-83.5115,"id":"Martins09922","taxonomy_updated_species":"Metlapilcoatlus_mexicanus","final_species":"Metlapilcoatlus_mexicanus","accuracy_m":"NA","flag":"","flag_detailed":""},{"lat":9.8423,"lng":-84.3156,"id":"Martins09923","taxonomy_updated_species":"Metlapilcoatlus_mexicanus","final_species":"Metlapilcoatlus_mexicanus","accuracy_m":"NA","flag":"","flag_detailed":""},{"lat":9.7687,"lng":-84.4012,"id":"Martins09924","taxonomy_updated_species":"Metlapilcoatlus_mexicanus","final_species":"Metlapilcoatlus_mexicanus","accuracy_m":"NA","flag":"","flag_detailed":""},{"lat":15.2929,"lng":-89.4716,"id":"Martins09932","taxonomy_updated_species":"Metlapilcoatlus_mexicanus","final_species":"Metlapilcoatlus_mexicanus","accuracy_m":"NA","flag":"","flag_detailed":""},{"lat":15.2932,"lng":-89.4716,"id":"Martins09933","taxonomy_updated_species":"Metlapilcoatlus_mexicanus","final_species":"Metlapilcoatlus_mexicanus","accuracy_m":"NA","flag":"","flag_detailed":""},{"lat":15.4782,"lng":-91.2367,"id":"Martins09934","taxonomy_updated_species":"Metlapilcoatlus_mexicanus","final_species":"Metlapilcoatlus_mexicanus","accuracy_m":"NA","flag":"geoDist","flag_detailed":"POTENTIAL_DUBIOUS_RECORD; DISTRIBUTION_ERROR; POINT_OUTSIDE_DISTRIBUTION; ADDITIONAL_CHECKS_NEEDED"},{"lat":15.1828,"lng":-90.2069,"id":"Martins09935","taxonomy_updated_species":"Metlapilcoatlus_mexicanus","final_species":"Metlapilcoatlus_mexicanus","accuracy_m":"NA","flag":"","flag_detailed":""},{"lat":15.6668,"lng":-89.2499,"id":"Martins09936","taxonomy_updated_species":"Metlapilcoatlus_mexicanus","final_species":"Metlapilcoatlus_mexicanus","accuracy_m":"NA","flag":"","flag_detailed":""},{"lat":15.6667,"lng":-89.25,"id":"Martins09937","taxonomy_updated_species":"Metlapilcoatlus_mexicanus","final_species":"Metlapilcoatlus_mexicanus","accuracy_m":"NA","flag":"","flag_detailed":""},{"lat":15.2557,"lng":-89.0968,"id":"Martins09941","taxonomy_updated_species":"Metlapilcoatlus_mexicanus","final_species":"Metlapilcoatlus_mexicanus","accuracy_m":"NA","flag":"","flag_detailed":""},{"lat":15.2557,"lng":-89.0967,"id":"Martins09942","taxonomy_updated_species":"Metlapilcoatlus_mexicanus","final_species":"Metlapilcoatlus_mexicanus","accuracy_m":"NA","flag":"","flag_detailed":""},{"lat":15.5832,"lng":-89.5836,"id":"Martins09945","taxonomy_updated_species":"Metlapilcoatlus_mexicanus","final_species":"Metlapilcoatlus_mexicanus","accuracy_m":"NA","flag":"","flag_detailed":""},{"lat":15.2929,"lng":-89.4716,"id":"Martins09946","taxonomy_updated_species":"Metlapilcoatlus_mexicanus","final_species":"Metlapilcoatlus_mexicanus","accuracy_m":"NA","flag":"","flag_detailed":""},{"lat":15.1667,"lng":-90.1,"id":"Martins09970","taxonomy_updated_species":"Metlapilcoatlus_mexicanus","final_species":"Metlapilcoatlus_mexicanus","accuracy_m":"NA","flag":"","flag_detailed":""},{"lat":15.137,"lng":-90.178,"id":"Martins09971","taxonomy_updated_species":"Metlapilcoatlus_mexicanus","final_species":"Metlapilcoatlus_mexicanus","accuracy_m":"NA","flag":"","flag_detailed":""},{"lat":15.7166,"lng":-88.5834,"id":"Martins09972","taxonomy_updated_species":"Metlapilcoatlus_mexicanus","final_species":"Metlapilcoatlus_mexicanus","accuracy_m":"NA","flag":"","flag_detailed":""},{"lat":15.7167,"lng":-88.5833,"id":"Martins09973","taxonomy_updated_species":"Metlapilcoatlus_mexicanus","final_species":"Metlapilcoatlus_mexicanus","accuracy_m":"NA","flag":"","flag_detailed":""},{"lat":16.9875,"lng":-89.9007,"id":"Martins09976","taxonomy_updated_species":"Metlapilcoatlus_mexicanus","final_species":"Metlapilcoatlus_mexicanus","accuracy_m":"NA","flag":"","flag_detailed":""},{"lat":16.9836,"lng":-89.901,"id":"Martins09977","taxonomy_updated_species":"Metlapilcoatlus_mexicanus","final_species":"Metlapilcoatlus_mexicanus","accuracy_m":"NA","flag":"","flag_detailed":""},{"lat":15.8639,"lng":-91.2683,"id":"Martins10018","taxonomy_updated_species":"Metlapilcoatlus_mexicanus","final_species":"Metlapilcoatlus_mexicanus","accuracy_m":"NA","flag":"","flag_detailed":""},{"lat":15.8071,"lng":-91.3147,"id":"Martins10019","taxonomy_updated_species":"Metlapilcoatlus_mexicanus","final_species":"Metlapilcoatlus_mexicanus","accuracy_m":"NA","flag":"","flag_detailed":""},{"lat":15.8828,"lng":-91.2503,"id":"Martins10020","taxonomy_updated_species":"Metlapilcoatlus_mexicanus","final_species":"Metlapilcoatlus_mexicanus","accuracy_m":"NA","flag":"","flag_detailed":""},{"lat":15.3481,"lng":-88.6772,"id":"Martins10021","taxonomy_updated_species":"Metlapilcoatlus_mexicanus","final_species":"Metlapilcoatlus_mexicanus","accuracy_m":"NA","flag":"","flag_detailed":""},{"lat":15.4718,"lng":-88.8445,"id":"Martins10029","taxonomy_updated_species":"Metlapilcoatlus_mexicanus","final_species":"Metlapilcoatlus_mexicanus","accuracy_m":"NA","flag":"","flag_detailed":""},{"lat":15.8865,"lng":-91.2455,"id":"Martins10034","taxonomy_updated_species":"Metlapilcoatlus_mexicanus","final_species":"Metlapilcoatlus_mexicanus","accuracy_m":"NA","flag":"","flag_detailed":""},{"lat":15.1828,"lng":-90.2069,"id":"Martins10087","taxonomy_updated_species":"Metlapilcoatlus_mexicanus","final_species":"Metlapilcoatlus_mexicanus","accuracy_m":"NA","flag":"","flag_detailed":""},{"lat":9.9027,"lng":-83.6231,"id":"Martins10095","taxonomy_updated_species":"Metlapilcoatlus_mexicanus","final_species":"Metlapilcoatlus_mexicanus","accuracy_m":"NA","flag":"","flag_detailed":""},{"lat":15.137,"lng":-90.178,"id":"Martins10111","taxonomy_updated_species":"Metlapilcoatlus_mexicanus","final_species":"Metlapilcoatlus_mexicanus","accuracy_m":"NA","flag":"","flag_detailed":""},{"lat":15.7167,"lng":-88.5833,"id":"Martins10112","taxonomy_updated_species":"Metlapilcoatlus_mexicanus","final_species":"Metlapilcoatlus_mexicanus","accuracy_m":"NA","flag":"","flag_detailed":""},{"lat":9.9011,"lng":-83.6846,"id":"Martins10134","taxonomy_updated_species":"Metlapilcoatlus_mexicanus","final_species":"Metlapilcoatlus_mexicanus","accuracy_m":"NA","flag":"","flag_detailed":""},{"lat":9.9087,"lng":-83.6232,"id":"Martins10135","taxonomy_updated_species":"Metlapilcoatlus_mexicanus","final_species":"Metlapilcoatlus_mexicanus","accuracy_m":"NA","flag":"","flag_detailed":""},{"lat":15.1385,"lng":-90.1787,"id":"Martins10152","taxonomy_updated_species":"Metlapilcoatlus_mexicanus","final_species":"Metlapilcoatlus_mexicanus","accuracy_m":"NA","flag":"","flag_detailed":""},{"lat":15.147,"lng":-90.1714,"id":"Martins10153","taxonomy_updated_species":"Metlapilcoatlus_mexicanus","final_species":"Metlapilcoatlus_mexicanus","accuracy_m":"NA","flag":"","flag_detailed":""},{"lat":15.7167,"lng":-88.5833,"id":"Martins10154","taxonomy_updated_species":"Metlapilcoatlus_mexicanus","final_species":"Metlapilcoatlus_mexicanus","accuracy_m":"NA","flag":"","flag_detailed":""},{"lat":15.7249,"lng":-88.5831,"id":"Martins10155","taxonomy_updated_species":"Metlapilcoatlus_mexicanus","final_species":"Metlapilcoatlus_mexicanus","accuracy_m":"NA","flag":"","flag_detailed":""}]
